Workbook

Sheet Car Listings
A1: Listing ID | B1: Brand | C1: Car Name | D1: Model | E1: Variant | F1: Manufacturing Year | G1: Registration Year | H1: New or Used | I1: Vehicle Type | J1: Fuel Type | K1: Transmission | L1: Number of Owners | M1: Selling Price (INR) | N1: Original Ex-Showroom Price (INR) | O1: Negotiable | P1: Minimum Expected Price (INR) | Q1: Down Payment (INR) | R1: Loan Amount (INR) | S1: Interest Rate (% per annum) | T1: EMI Tenure (Months) | U1: Estimated Monthly EMI (INR) | V1: Loan Eligible | W1: Engine Capacity (cc) | X1: Maximum Power (bhp) | Y1: Mileage (km/l) | Z1: Range (km per charge for EVs) | AA1: Battery Capacity (kWh, for EVs) | AB1: Seating Capacity | AC1: Number of Doors | AD1: Boot Space (litres) | AE1: Safety Rating | AF1: Airbags | AG1: ABS | AH1: Rear Camera | AI1: Parking Sensors | AJ1: Exterior Colour | AK1: Vehicle Condition | AL1: Odometer Reading (km) | AM1: Insurance Valid Until | AN1: Registration State | AO1: City | AP1: Availability Status | AQ1: Listing Date | AR1: Seller Type | AS1: Service History Available | AT1: Warranty Available | AU1: Accident History Disclosed | AV1: Key Features | AW1: Description | AX1: Suitable Buyer | AY1: Estimated Annual Maintenance Cost (INR) | AZ1: Source Type | BA1: Source URL
A2: CAR-1001 | B2: Maruti Suzuki | C2: Maruti Suzuki Swift | D2: Swift | E2: ZXi+ 1.2L DualJet | F2: 2018 | G2: 2019 | H2: Used | I2: Hatchback | J2: Petrol | K2: Manual | L2: 3 | M2: 295000 | N2: 720000 | O2: No | P2: 295000 | Q2: 75000 | R2: =IF(V2="No",0,MAX(0,M2-Q2)) -> 220000 | S2: 11.45 | T2: 36 | U2: =IF(OR(R2<=0,S2<0,T2<=0),"",IF(S2=0,R2/T2,-PMT(S2/1200,T2,R2))) -> 7249 | V2: Yes | W2: 1197 | X2: 89 | Y2: 22.38 | AB2: 5 | AC2: 5 | AD2: 268 | AF2: 6 | AG2: Yes | AH2: Yes | AI2: Yes | AJ2: Pearl Arctic White | AK2: Fair | AL2: 95500 | AM2: 2027-01-01 | AN2: Tamil Nadu | AO2: Chennai | AP2: Available | AQ2: 2026-10-01 | AR2: Individual | AS2: No | AT2: No | AU2: Unknown | AV2: SmartPlay Pro+ 9-inch Touchscreen, Cruise Control, LED Projector Headlamps, Auto AC | AW2: Well-maintained 2018 fair condition Maruti Suzuki Swift ZXi+ 1.2L DualJet (Manual) in Chennai. Powered by a 1197 cc petrol engine delivering 22.38 km/l. Inspected for mechanical reliability. | AX2: Daily Commuter | AY2: 8600 | AZ2: Synthetic Sample
A3: CAR-1002 | B3: Maruti Suzuki | C3: Maruti Suzuki Baleno | D3: Baleno | E3: Alpha 1.2L AGS | F3: 2025 | G3: 2025 | H3: Used | I3: Hatchback | J3: Petrol | K3: AMT | L3: 1 | M3: 875000 | N3: 965000 | O3: Yes | P3: 830000 | Q3: 220000 | R3: =IF(V3="No",0,MAX(0,M3-Q3)) -> 655000 | S3: 10.4 | T3: 48 | U3: =IF(OR(R3<=0,S3<0,T3<=0),"",IF(S3=0,R3/T3,-PMT(S3/1200,T3,R3))) -> 16739 | V3: Yes | W3: 1197 | X3: 89 | Y3: 22.94 | AB3: 5 | AC3: 5 | AD3: 318 | AE3: 4 Star (Bharat NCAP) | AF3: 6 | AG3: Yes | AH3: Yes | AI3: Yes | AJ3: Titan Grey | AK3: Like New | AL3: 10200 | AM3: 2026-12-06 | AN3: Karnataka | AO3: Bengaluru | AP3: Available | AQ3: 2026-09-04 | AR3: Dealer | AS3: Yes | AT3: Yes | AU3: No | AV3: Head-Up Display, 360 View Camera, 9-inch SmartPlay Pro+, UV Cut Glass | AW3: Well-maintained 2025 like new condition Maruti Suzuki Baleno Alpha 1.2L AGS (AMT) in Bengaluru. Powered by a 1197 cc petrol engine delivering 22.94 km/l. Complete service history available. | AX3: Family | AY3: 7100 | AZ3: Synthetic Sample
A4: CAR-1003 | B4: Maruti Suzuki | C4: Maruti Suzuki Brezza | D4: Brezza | E4: ZXi+ 1.5L Smart Hybrid AT | F4: 2020 | G4: 2020 | H4: Used | I4: SUV | J4: Petrol | K4: Automatic | L4: 1 | M4: 655000 | N4: 1190000 | O4: Yes | P4: 630000 | Q4: 165000 | R4: =IF(V4="No",0,MAX(0,M4-Q4)) -> 490000 | S4: 11.15 | T4: 60 | U4: =IF(OR(R4<=0,S4<0,T4<=0),"",IF(S4=0,R4/T4,-PMT(S4/1200,T4,R4))) -> 10690 | V4: Yes | W4: 1462 | X4: 102 | Y4: 19.8 | AB4: 5 | AC4: 5 | AD4: 328 | AE4: 4 Star (Global NCAP) | AF4: 6 | AG4: Yes | AH4: Yes | AI4: Yes | AJ4: Abyss Black | AK4: Excellent | AL4: 54300 | AM4: 2027-03-11 | AN4: Telangana | AO4: Hyderabad | AP4: Available | AQ4: 2026-10-07 | AR4: Dealer | AS4: Yes | AT4: No | AU4: No | AV4: Electric Sunroof, Paddle Shifters, 360 Degree Camera, Wireless Charging | AW4: Well-maintained 2020 excellent condition Maruti Suzuki Brezza ZXi+ 1.5L Smart Hybrid AT (Automatic) in Hyderabad. Powered by a 1462 cc petrol engine delivering 19.8 km/l. Complete service history available. | AX4: Family | AY4: 10200 | AZ4: Synthetic Sample
A5: CAR-1004 | B5: Maruti Suzuki | C5: Maruti Suzuki Wagon R | D5: Wagon R | E5: VXi 1.0L S-CNG | F5: 2015 | G5: 2015 | H5: Used | I5: Hatchback | J5: CNG | K5: Manual | L5: 2 | M5: 150000 | N5: 500000 | O5: No | P5: 150000 | Q5: 40000 | R5: =IF(V5="No",0,MAX(0,M5-Q5)) -> 0 | S5: 0 | T5: 0 | U5: =IF(OR(R5<=0,S5<0,T5<=0),"",IF(S5=0,R5/T5,-PMT(S5/1200,T5,R5))) | V5: No | W5: 998 | X5: 56 | Y5: 33.47 | AB5: 5 | AC5: 5 | AD5: 341 | AF5: 2 | AG5: Yes | AH5: No | AI5: Yes | AJ5: Starry Night Blue | AK5: Fair | AL5: 139700 | AM5: 2026-12-16 | AN5: Maharashtra | AO5: Mumbai | AP5: Available | AQ5: 2026-09-10 | AR5: Individual | AS5: Yes | AT5: No | AU5: No | AV5: Factory Fitted S-CNG Dual Interdependent ECUs, Keyless Entry, Power Windows | AW5: Well-maintained 2015 fair condition Maruti Suzuki Wagon R VXi 1.0L S-CNG (Manual) in Mumbai. Powered by a 998 cc cng engine delivering 33.47 km/l. Complete service history available. | AX5: First-Time Buyer | AY5: 7900 | AZ5: Synthetic Sample
A6: CAR-1005 | B6: Maruti Suzuki | C6: Maruti Suzuki Ertiga | D6: Ertiga | E6: ZXi 1.5L S-CNG | F6: 2022 | G6: 2022 | H6: Used | I6: MUV | J6: CNG | K6: Manual | L6: 1 | M6: 720000 | N6: 1070000 | O6: Yes | P6: 685000 | Q6: 180000 | R6: =IF(V6="No",0,MAX(0,M6-Q6)) -> 540000 | S6: 10.85 | T6: 48 | U6: =IF(OR(R6<=0,S6<0,T6<=0),"",IF(S6=0,R6/T6,-PMT(S6/1200,T6,R6))) -> 13917 | V6: Yes | W6: 1462 | X6: 87 | Y6: 26.11 | AB6: 7 | AC6: 5 | AD6: 209 | AF6: 4 | AG6: Yes | AH6: Yes | AI6: Yes | AJ6: Pearl Arctic White | AK6: Excellent | AL6: 56700 | AM6: 2027-05-21 | AN6: Delhi | AO6: Delhi | AP6: Reserved | AQ6: 2026-10-13 | AR6: Dealer | AS6: Yes | AT6: Yes | AU6: No | AV6: 7-Seater Reclining Rows, Roof Mounted AC Vents, 7-inch SmartPlay Studio | AW6: Well-maintained 2022 excellent condition Maruti Suzuki Ertiga ZXi 1.5L S-CNG (Manual) in Delhi. Powered by a 1462 cc cng engine delivering 26.11 km/l. Complete service history available. | AX6: Family | AY6: 9000 | AZ6: Synthetic Sample
A7: CAR-1006 | B7: Maruti Suzuki | C7: Maruti Suzuki Grand Vitara | D7: Grand Vitara | E7: Alpha+ 1.5L Intelligent Electric Hybrid | F7: 2024 | G7: 2025 | H7: Used | I7: SUV | J7: Hybrid | K7: CVT | L7: 1 | M7: 1555000 | N7: 1900000 | O7: Yes | P7: 1495000 | Q7: 390000 | R7: =IF(V7="No",0,MAX(0,M7-Q7)) -> 1165000 | S7: 10.55 | T7: 60 | U7: =IF(OR(R7<=0,S7<0,T7<=0),"",IF(S7=0,R7/T7,-PMT(S7/1200,T7,R7))) -> 25069 | V7: Yes | W7: 1490 | X7: 114 | Y7: 27.97 | AB7: 5 | AC7: 5 | AD7: 265 | AE7: 5 Star (Bharat NCAP) | AF7: 6 | AG7: Yes | AH7: Yes | AI7: Yes | AJ7: Titan Grey | AK7: Like New | AL7: 23200 | AM7: 2026-12-26 | AN7: Maharashtra | AO7: Pune | AP7: Sold | AQ7: 2026-09-16 | AR7: Dealer | AS7: Yes | AT7: Yes | AU7: No | AV7: Panoramic Sunroof, Ventilated Front Seats, Strong Hybrid e-CVT, TPMS | AW7: Well-maintained 2024 like new condition Maruti Suzuki Grand Vitara Alpha+ 1.5L Intelligent Electric Hybrid (CVT) in Pune. Powered by a 1490 cc hybrid engine delivering 27.97 km/l. Complete service history available. | AX7: Family | AY7: 9900 | AZ7: Synthetic Sample
A8: CAR-1007 | B8: Maruti Suzuki | C8: Maruti Suzuki Dzire | D8: Dzire | E8: ZXi+ 1.2L AGS | F8: 2024 | G8: 2024 | H8: Used | I8: Sedan | J8: Petrol | K8: AMT | L8: 1 | M8: 790000 | N8: 965000 | O8: No | P8: 790000 | Q8: 200000 | R8: =IF(V8="No",0,MAX(0,M8-Q8)) -> 590000 | S8: 10.55 | T8: 36 | U8: =IF(OR(R8<=0,S8<0,T8<=0),"",IF(S8=0,R8/T8,-PMT(S8/1200,T8,R8))) -> 19190 | V8: Yes | W8: 1197 | X8: 80 | Y8: 25.71 | AB8: 5 | AC8: 4 | AD8: 382 | AE8: 5 Star (Global NCAP) | AF8: 6 | AG8: Yes | AH8: Yes | AI8: Yes | AJ8: Abyss Black | AK8: Like New | AL8: 21500 | AM8: 2027-07-04 | AN8: Tamil Nadu | AO8: Coimbatore | AP8: Available | AQ8: 2026-10-19 | AR8: Individual | AS8: Yes | AT8: Yes | AU8: No | AV8: Electric Sunroof, 360 HD View Camera, Wireless Android Auto & CarPlay | AW8: Well-maintained 2024 like new condition Maruti Suzuki Dzire ZXi+ 1.2L AGS (AMT) in Coimbatore. Powered by a 1197 cc petrol engine delivering 25.71 km/l. Complete service history available. | AX8: Family | AY8: 7100 | AZ8: Synthetic Sample
A9: CAR-1008 | B9: Hyundai | C9: Hyundai Creta | D9: Creta | E9: SX (O) 1.5L Turbo GDi DCT | F9: 2019 | G9: 2019 | H9: Used | I9: SUV | J9: Petrol | K9: DCT | L9: 1 | M9: 825000 | N9: 1660000 | O9: Yes | P9: 785000 | Q9: 205000 | R9: =IF(V9="No",0,MAX(0,M9-Q9)) -> 620000 | S9: 11.3 | T9: 48 | U9: =IF(OR(R9<=0,S9<0,T9<=0),"",IF(S9=0,R9/T9,-PMT(S9/1200,T9,R9))) -> 16115 | V9: Yes | W9: 1482 | X9: 158 | Y9: 18.4 | AB9: 5 | AC9: 5 | AD9: 433 | AF9: 6 | AG9: Yes | AH9: Yes | AI9: Yes | AJ9: Starry Night Blue | AK9: Good | AL9: 68500 | AM9: 2026-12-09 | AN9: Kerala | AO9: Kochi | AP9: Available | AQ9: 2026-09-22 | AR9: Dealer | AS9: No | AT9: No | AU9: No | AV9: Level 2 ADAS, Bose 8-Speaker Audio, Panoramic Sunroof, Dual 10.25-inch Displays | AW9: Well-maintained 2019 good condition Hyundai Creta SX (O) 1.5L Turbo GDi DCT (DCT) in Kochi. Powered by a 1482 cc petrol engine delivering 18.4 km/l. Inspected for mechanical reliability. | AX9: Family | AY9: 12500 | AZ9: Synthetic Sample
A10: CAR-1009 | B10: Hyundai | C10: Hyundai Creta | D10: Creta | E10: SX Tech 1.5L CRDi AT | F10: 2026 | G10: 2026 | H10: New | I10: SUV | J10: Diesel | K10: Automatic | L10: 0 | M10: 1910000 | N10: 1910000 | O10: Yes | P10: 1835000 | Q10: 380000 | R10: =IF(V10="No",0,MAX(0,M10-Q10)) -> 1530000 | S10: 8.95 | T10: 84 | U10: =IF(OR(R10<=0,S10<0,T10<=0),"",IF(S10=0,R10/T10,-PMT(S10/1200,T10,R10))) -> 24577 | V10: Yes | W10: 1493 | X10: 114 | Y10: 19.1 | AB10: 5 | AC10: 5 | AD10: 433 | AF10: 6 | AG10: Yes | AH10: Yes | AI10: Yes | AJ10: Pearl Arctic White | AK10: New | AL10: 23 | AM10: 2029-09-14 | AN10: Gujarat | AO10: Ahmedabad | AP10: Available | AQ10: 2026-10-03 | AR10: Dealer | AS10: Yes | AT10: Yes | AU10: No | AV10: Panoramic Sunroof, Voice Enabled Smart Controls, Bose Sound, Bluelink Connected Car | AW10: Brand-new 2026 showroom condition Hyundai Creta SX Tech 1.5L CRDi AT (Automatic) in Ahmedabad. Powered by a 1493 cc diesel engine delivering 19.1 km/l. Complete service history available. | AX10: Family | AY10: 10500 | AZ10: Synthetic Sample
A11: CAR-1010 | B11: Hyundai | C11: Hyundai i20 | D11: i20 | E11: Asta (O) 1.2L Kappa IVT | F11: 2021 | G11: 2021 | H11: Used | I11: Hatchback | J11: Petrol | K11: CVT | L11: 2 | M11: 595000 | N11: 980000 | O11: No | P11: 595000 | Q11: 150000 | R11: =IF(V11="No",0,MAX(0,M11-Q11)) -> 445000 | S11: 11 | T11: 36 | U11: =IF(OR(R11<=0,S11<0,T11<=0),"",IF(S11=0,R11/T11,-PMT(S11/1200,T11,R11))) -> 14569 | V11: Yes | W11: 1197 | X11: 87 | Y11: 19.65 | AB11: 5 | AC11: 5 | AD11: 311 | AE11: 3 Star (Global NCAP) | AF11: 6 | AG11: Yes | AH11: Yes | AI11: Yes | AJ11: Titan Grey | AK11: Excellent | AL11: 50200 | AM11: 2026-12-19 | AN11: West Bengal | AO11: Kolkata | AP11: Available | AQ11: 2026-09-06 | AR11: Individual | AS11: Yes | AT11: No | AU11: No | AV11: Electric Sunroof, Bose 7-Speaker System, 10.25-inch HD Infotainment, Ambient Lighting | AW11: Well-maintained 2021 excellent condition Hyundai i20 Asta (O) 1.2L Kappa IVT (CVT) in Kolkata. Powered by a 1197 cc petrol engine delivering 19.65 km/l. Complete service history available. | AX11: Daily Commuter | AY11: 8900 | AZ11: Synthetic Sample
A12: CAR-1011 | B12: Hyundai | C12: Hyundai Verna | D12: Verna | E12: SX (O) 1.5L Turbo GDi DCT | F12: 2016 | G12: 2017 | H12: Used | I12: Sedan | J12: Petrol | K12: DCT | L12: 2 | M12: 480000 | N12: 1305000 | O12: Yes | P12: 455000 | Q12: 120000 | R12: =IF(V12="No",0,MAX(0,M12-Q12)) -> 360000 | S12: 11.75 | T12: 48 | U12: =IF(OR(R12<=0,S12<0,T12<=0),"",IF(S12=0,R12/T12,-PMT(S12/1200,T12,R12))) -> 9436 | V12: Yes | W12: 1482 | X12: 158 | Y12: 20.6 | AB12: 5 | AC12: 4 | AD12: 528 | AE12: 5 Star (Global NCAP) | AF12: 6 | AG12: Yes | AH12: Yes | AI12: Yes | AJ12: Abyss Black | AK12: Good | AL12: 76700 | AM12: 2027-11-24 | AN12: Tamil Nadu | AO12: Chennai | AP12: Reserved | AQ12: 2026-10-09 | AR12: Dealer | AS12: Yes | AT12: No | AU12: No | AV12: Hyundai SmartSense Level 2 ADAS, Heated & Ventilated Front Seats, Horizon LED Lamp | AW12: Well-maintained 2016 good condition Hyundai Verna SX (O) 1.5L Turbo GDi DCT (DCT) in Chennai. Powered by a 1482 cc petrol engine delivering 20.6 km/l. Complete service history available. | AX12: Enthusiast | AY12: 12700 | AZ12: Synthetic Sample
A13: CAR-1012 | B13: Hyundai | C13: Hyundai Venue | D13: Venue | E13: SX (O) 1.0L Turbo DCT | F13: 2023 | G13: 2023 | H13: Used | I13: SUV | J13: Petrol | K13: DCT | L13: 1 | M13: 925000 | N13: 1245000 | O13: Yes | P13: 890000 | Q13: 230000 | R13: =IF(V13="No",0,MAX(0,M13-Q13)) -> 695000 | S13: 10.7 | T13: 60 | U13: =IF(OR(R13<=0,S13<0,T13<=0),"",IF(S13=0,R13/T13,-PMT(S13/1200,T13,R13))) -> 15007 | V13: Yes | W13: 998 | X13: 118 | Y13: 18.31 | AB13: 5 | AC13: 5 | AD13: 350 | AF13: 6 | AG13: Yes | AH13: Yes | AI13: Yes | AJ13: Starry Night Blue | AK13: Excellent | AL13: 28800 | AM13: 2026-12-02 | AN13: Karnataka | AO13: Bengaluru | AP13: Sold | AQ13: 2026-09-12 | AR13: Dealer | AS13: Yes | AT13: Yes | AU13: No | AV13: Smart Electric Sunroof, 4-Way Power Driver Seat, Air Purifier, Dashcam | AW13: Well-maintained 2023 excellent condition Hyundai Venue SX (O) 1.0L Turbo DCT (DCT) in Bengaluru. Powered by a 998 cc petrol engine delivering 18.31 km/l. Complete service history available. | AX13: Daily Commuter | AY13: 9000 | AZ13: Synthetic Sample
A14: CAR-1013 | B14: Hyundai | C14: Hyundai Ioniq 5 | D14: Ioniq 5 | E14: RWD 72.6 kWh Long Range | F14: 2023 | G14: 2023 | H14: Used | I14: SUV | J14: Electric | K14: Automatic | L14: 1 | M14: 3160000 | N14: 4260000 | O14: No | P14: 3160000 | Q14: 790000 | R14: =IF(V14="No",0,MAX(0,M14-Q14)) -> 2370000 | S14: 10.7 | T14: 36 | U14: =IF(OR(R14<=0,S14<0,T14<=0),"",IF(S14=0,R14/T14,-PMT(S14/1200,T14,R14))) -> 77254 | V14: Yes | X14: 215 | Z14: 631 | AA14: 72.6 | AB14: 5 | AC14: 5 | AD14: 527 | AE14: 5 Star (Euro NCAP) | AF14: 6 | AG14: Yes | AH14: Yes | AI14: Yes | AJ14: Pearl Arctic White | AK14: Like New | AL14: 26900 | AM14: 2027-01-07 | AN14: Telangana | AO14: Hyderabad | AP14: Available | AQ14: 2026-10-15 | AR14: Individual | AS14: Yes | AT14: Yes | AU14: No | AV14: 800V Ultra-Fast Charging, Vehicle-to-Load (V2L), Parametric Pixel LED, Level 2 ADAS | AW14: Well-maintained 2023 like new condition Hyundai Ioniq 5 RWD 72.6 kWh Long Range (Automatic) in Hyderabad. Powered by a 72.6 kWh battery delivering 631 km certified range. Complete service history available. | AX14: Enthusiast | AY14: 6900 | AZ14: Synthetic Sample
A15: CAR-1014 | B15: Hyundai | C15: Hyundai Grand i10 Nios | D15: Grand i10 Nios | E15: Sportz 1.2L Hy-CNG Duo | F15: 2025 | G15: 2025 | H15: Used | I15: Hatchback | J15: CNG | K15: Manual | L15: 1 | M15: 735000 | N15: 810000 | O15: Yes | P15: 700000 | Q15: 185000 | R15: =IF(V15="No",0,MAX(0,M15-Q15)) -> 550000 | S15: 10.4 | T15: 48 | U15: =IF(OR(R15<=0,S15<0,T15<=0),"",IF(S15=0,R15/T15,-PMT(S15/1200,T15,R15))) -> 14055 | V15: Yes | W15: 1197 | X15: 68 | Y15: 27.3 | AB15: 5 | AC15: 5 | AD15: 240 | AF15: 6 | AG15: Yes | AH15: Yes | AI15: Yes | AJ15: Titan Grey | AK15: Like New | AL15: 12400 | AM15: 2026-12-12 | AN15: Maharashtra | AO15: Mumbai | AP15: Available | AQ15: 2026-09-18 | AR15: Dealer | AS15: Yes | AT15: Yes | AU15: No | AV15: Dual Cylinder CNG with Usable Boot, 8-inch Touchscreen, Rear AC Vents | AW15: Well-maintained 2025 like new condition Hyundai Grand i10 Nios Sportz 1.2L Hy-CNG Duo (Manual) in Mumbai. Powered by a 1197 cc cng engine delivering 27.3 km/l. Complete service history available. | AX15: First-Time Buyer | AY15: 6400 | AZ15: Synthetic Sample
A16: CAR-1015 | B16: Tata | C16: Tata Nexon | D16: Nexon | E16: Fearless+ S 1.2L Turbo DCA | F16: 2020 | G16: 2020 | H16: Used | I16: SUV | J16: Petrol | K16: DCT | L16: 1 | M16: 690000 | N16: 1260000 | O16: Yes | P16: 660000 | Q16: 175000 | R16: =IF(V16="No",0,MAX(0,M16-Q16)) -> 515000 | S16: 11.15 | T16: 60 | U16: =IF(OR(R16<=0,S16<0,T16<=0),"",IF(S16=0,R16/T16,-PMT(S16/1200,T16,R16))) -> 11236 | V16: Yes | W16: 1199 | X16: 118 | Y16: 17.01 | AB16: 5 | AC16: 5 | AD16: 382 | AE16: 5 Star (Global & Bharat NCAP) | AF16: 6 | AG16: Yes | AH16: Yes | AI16: Yes | AJ16: Abyss Black | AK16: Excellent | AL16: 60500 | AM16: 2027-03-17 | AN16: Delhi | AO16: Delhi | AP16: Available | AQ16: 2026-10-21 | AR16: Dealer | AS16: No | AT16: No | AU16: No | AV16: 10.25-inch Harman Floating Infotainment, 360 Surround View, Ventilated Seats, JBL Audio | AW16: Well-maintained 2020 excellent condition Tata Nexon Fearless+ S 1.2L Turbo DCA (DCT) in Delhi. Powered by a 1199 cc petrol engine delivering 17.01 km/l. Inspected for mechanical reliability. | AX16: Family | AY16: 10500 | AZ16: Synthetic Sample
A17: CAR-1016 | B17: Tata | C17: Tata Nexon.ev | D17: Nexon.ev | E17: Empowered+ 45 kWh Long Range | F17: 2024 | G17: 2025 | H17: Used | I17: SUV | J17: Electric | K17: Automatic | L17: 1 | M17: 1325000 | N17: 1615000 | O17: No | P17: 1325000 | Q17: 330000 | R17: =IF(V17="No",0,MAX(0,M17-Q17)) -> 995000 | S17: 10.55 | T17: 36 | U17: =IF(OR(R17<=0,S17<0,T17<=0),"",IF(S17=0,R17/T17,-PMT(S17/1200,T17,R17))) -> 32363 | V17: Yes | X17: 142 | Z17: 489 | AA17: 45 | AB17: 5 | AC17: 5 | AD17: 350 | AE17: 5 Star (Bharat NCAP) | AF17: 6 | AG17: Yes | AH17: Yes | AI17: Yes | AJ17: Starry Night Blue | AK17: Like New | AL17: 18300 | AM17: 2026-12-22 | AN17: Maharashtra | AO17: Pune | AP17: Available | AQ17: 2026-09-02 | AR17: Individual | AS17: Yes | AT17: Yes | AU17: Unknown | AV17: Panoramic Sunroof, V2V & V2L Charging, 12.3-inch Cinematic Screen, Arcade.ev App Suite | AW17: Well-maintained 2024 like new condition Tata Nexon.ev Empowered+ 45 kWh Long Range (Automatic) in Pune. Powered by a 45 kWh battery delivering 489 km certified range. Complete service history available. | AX17: Daily Commuter | AY17: 5200 | AZ17: Synthetic Sample
A18: CAR-1017 | B18: Tata | C18: Tata Punch | D18: Punch | E18: Accomplished+ S iCNG | F18: 2022 | G18: 2022 | H18: Used | I18: SUV | J18: CNG | K18: Manual | L18: 1 | M18: 595000 | N18: 885000 | O18: Yes | P18: 565000 | Q18: 150000 | R18: =IF(V18="No",0,MAX(0,M18-Q18)) -> 445000 | S18: 10.85 | T18: 48 | U18: =IF(OR(R18<=0,S18<0,T18<=0),"",IF(S18=0,R18/T18,-PMT(S18/1200,T18,R18))) -> 11469 | V18: Yes | W18: 1199 | X18: 72 | Y18: 26.99 | AB18: 5 | AC18: 5 | AD18: 210 | AE18: 5 Star (Global NCAP) | AF18: 2 | AG18: Yes | AH18: Yes | AI18: Yes | AJ18: Pearl Arctic White | AK18: Excellent | AL18: 60900 | AM18: 2027-05-27 | AN18: Tamil Nadu | AO18: Coimbatore | AP18: Reserved | AQ18: 2026-10-05 | AR18: Dealer | AS18: Yes | AT18: Yes | AU18: No | AV18: Twin-Cylinder iCNG Technology, Voice Assisted Electric Sunroof, 7-inch Harman Screen | AW18: Well-maintained 2022 excellent condition Tata Punch Accomplished+ S iCNG (Manual) in Coimbatore. Powered by a 1199 cc cng engine delivering 26.99 km/l. Complete service history available. | AX18: First-Time Buyer | AY18: 7400 | AZ18: Synthetic Sample
A19: CAR-1018 | B19: Tata | C19: Tata Punch.ev | D19: Punch.ev | E19: Empowered+ S 35 kWh Long Range | F19: 2024 | G19: 2024 | H19: Used | I19: SUV | J19: Electric | K19: Automatic | L19: 1 | M19: 1125000 | N19: 1375000 | O19: Yes | P19: 1080000 | Q19: 280000 | R19: =IF(V19="No",0,MAX(0,M19-Q19)) -> 845000 | S19: 10.55 | T19: 60 | U19: =IF(OR(R19<=0,S19<0,T19<=0),"",IF(S19=0,R19/T19,-PMT(S19/1200,T19,R19))) -> 18183 | V19: Yes | X19: 120 | Z19: 421 | AA19: 35 | AB19: 5 | AC19: 5 | AD19: 366 | AE19: 5 Star (Bharat NCAP) | AF19: 6 | AG19: Yes | AH19: Yes | AI19: Yes | AJ19: Titan Grey | AK19: Like New | AL19: 18100 | AM19: 2026-12-05 | AN19: Kerala | AO19: Kochi | AP19: Sold | AQ19: 2026-09-08 | AR19: Dealer | AS19: Yes | AT19: Yes | AU19: No | AV19: acti.ev Pure EV Architecture, Frunk Storage, 360 Camera, Electronic Parking Brake | AW19: Well-maintained 2024 like new condition Tata Punch.ev Empowered+ S 35 kWh Long Range (Automatic) in Kochi. Powered by a 35 kWh battery delivering 421 km certified range. Complete service history available. | AX19: Daily Commuter | AY19: 4900 | AZ19: Synthetic Sample
A20: CAR-1019 | B20: Tata | C20: Tata Harrier | D20: Harrier | E20: Fearless+ Dark 2.0L Kryotec AT | F20: 2024 | G20: 2024 | H20: Used | I20: SUV | J20: Diesel | K20: Automatic | L20: 1 | M20: 2045000 | N20: 2495000 | O20: No | P20: 2045000 | Q20: 510000 | R20: =IF(V20="No",0,MAX(0,M20-Q20)) -> 1535000 | S20: 10.55 | T20: 36 | U20: =IF(OR(R20<=0,S20<0,T20<=0),"",IF(S20=0,R20/T20,-PMT(S20/1200,T20,R20))) -> 49927 | V20: Yes | W20: 1956 | X20: 168 | Y20: 16.8 | AB20: 5 | AC20: 5 | AD20: 445 | AE20: 5 Star (Global & Bharat NCAP) | AF20: 7 | AG20: Yes | AH20: Yes | AI20: Yes | AJ20: Abyss Black | AK20: Like New | AL20: 21500 | AM20: 2027-07-10 | AN20: Gujarat | AO20: Ahmedabad | AP20: Available | AQ20: 2026-10-11 | AR20: Individual | AS20: Yes | AT20: Yes | AU20: No | AV20: ADAS Level 2, Gesture Controlled Powered Tailgate, Dual-Zone Climate Control, Panoramic Sunroof | AW20: Well-maintained 2024 like new condition Tata Harrier Fearless+ Dark 2.0L Kryotec AT (Automatic) in Ahmedabad. Powered by a 1956 cc diesel engine delivering 16.8 km/l. Complete service history available. | AX20: Family | AY20: 13500 | AZ20: Synthetic Sample
A21: CAR-1020 | B21: Tata | C21: Tata Safari | D21: Safari | E21: Accomplished+ 2.0L Kryotec AT 6S | F21: 2019 | G21: 2019 | H21: Used | I21: SUV | J21: Diesel | K21: Automatic | L21: 1 | M21: 1020000 | N21: 2255000 | O21: Yes | P21: 970000 | Q21: 255000 | R21: =IF(V21="No",0,MAX(0,M21-Q21)) -> 765000 | S21: 11.3 | T21: 48 | U21: =IF(OR(R21<=0,S21<0,T21<=0),"",IF(S21=0,R21/T21,-PMT(S21/1200,T21,R21))) -> 19883 | V21: Yes | W21: 1956 | X21: 168 | Y21: 16.3 | AB21: 6 | AC21: 5 | AD21: 420 | AE21: 5 Star (Global & Bharat NCAP) | AF21: 7 | AG21: Yes | AH21: Yes | AI21: Yes | AJ21: Starry Night Blue | AK21: Fair | AL21: 112400 | AM21: 2026-12-15 | AN21: West Bengal | AO21: Kolkata | AP21: Available | AQ21: 2026-09-14 | AR21: Dealer | AS21: Yes | AT21: No | AU21: No | AV21: 2nd Row Ventilated Captain Seats, Boss Mode, 10-Speaker JBL Dolby Atmos, Panoramic Sunroof | AW21: Well-maintained 2019 fair condition Tata Safari Accomplished+ 2.0L Kryotec AT 6S (Automatic) in Kolkata. Powered by a 1956 cc diesel engine delivering 16.3 km/l. Complete service history available. | AX21: Family | AY21: 16900 | AZ21: Synthetic Sample
A22: CAR-1021 | B22: Tata | C22: Tata Curvv.ev | D22: Curvv.ev | E22: Empowered+ A 55 kWh | F22: 2023 | G22: 2024 | H22: Used | I22: Coupe | J22: Electric | K22: Automatic | L22: 1 | M22: 1510000 | N22: 2035000 | O22: Yes | P22: 1450000 | Q22: 380000 | R22: =IF(V22="No",0,MAX(0,M22-Q22)) -> 1130000 | S22: 10.7 | T22: 60 | U22: =IF(OR(R22<=0,S22<0,T22<=0),"",IF(S22=0,R22/T22,-PMT(S22/1200,T22,R22))) -> 24400 | V22: Yes | X22: 165 | Z22: 585 | AA22: 55 | AB22: 5 | AC22: 5 | AD22: 500 | AE22: 5 Star (Bharat NCAP) | AF22: 6 | AG22: Yes | AH22: Yes | AI22: Yes | AJ22: Pearl Arctic White | AK22: Like New | AL22: 23800 | AM22: 2027-09-20 | AN22: Tamil Nadu | AO22: Chennai | AP22: Available | AQ22: 2026-10-17 | AR22: Dealer | AS22: Yes | AT22: Yes | AU22: No | AV22: SUV Coupe Design, Level 2 ADAS (20 Features), Acoustic Vehicle Alert System, Powered Tailgate | AW22: Well-maintained 2023 like new condition Tata Curvv.ev Empowered+ A 55 kWh (Automatic) in Chennai. Powered by a 55 kWh battery delivering 585 km certified range. Complete service history available. | AX22: Enthusiast | AY22: 5800 | AZ22: Synthetic Sample
A23: CAR-1022 | B23: Mahindra | C23: Mahindra XUV700 | D23: XUV700 | E23: AX7 Luxury Pack 2.2L mHawk AT AWD | F23: 2021 | G23: 2021 | H23: Used | I23: SUV | J23: Diesel | K23: Automatic | L23: 2 | M23: 1355000 | N23: 2230000 | O23: No | P23: 1355000 | Q23: 340000 | R23: =IF(V23="No",0,MAX(0,M23-Q23)) -> 1015000 | S23: 11 | T23: 36 | U23: =IF(OR(R23<=0,S23<0,T23<=0),"",IF(S23=0,R23/T23,-PMT(S23/1200,T23,R23))) -> 33230 | V23: Yes | W23: 2198 | X23: 182 | Y23: 15.5 | AB23: 7 | AC23: 5 | AD23: 240 | AE23: 5 Star (Global NCAP) | AF23: 7 | AG23: Yes | AH23: Yes | AI23: Yes | AJ23: Titan Grey | AK23: Excellent | AL23: 54500 | AM23: 2026-12-25 | AN23: Karnataka | AO23: Bengaluru | AP23: Available | AQ23: 2026-09-20 | AR23: Individual | AS23: No | AT23: No | AU23: No | AV23: Skyroof Panoramic Sunroof, Adrenox Dual 10.25-inch Screens, Sony 12-Speaker 3D Audio, ADAS | AW23: Well-maintained 2021 excellent condition Mahindra XUV700 AX7 Luxury Pack 2.2L mHawk AT AWD (Automatic) in Bengaluru. Powered by a 2198 cc diesel engine delivering 15.5 km/l. Inspected for mechanical reliability. | AX23: Family | AY23: 15400 | AZ23: Synthetic Sample
A24: CAR-1023 | B24: Mahindra | C24: Mahindra Scorpio-N | D24: Scorpio-N | E24: Z8L 2.2L mHawk 4XPLOR AT | F24: 2016 | G24: 2016 | H24: Used | I24: SUV | J24: Diesel | K24: Automatic | L24: 2 | M24: 615000 | N24: 1840000 | O24: Yes | P24: 585000 | Q24: 155000 | R24: =IF(V24="No",0,MAX(0,M24-Q24)) -> 460000 | S24: 11.75 | T24: 48 | U24: =IF(OR(R24<=0,S24<0,T24<=0),"",IF(S24=0,R24/T24,-PMT(S24/1200,T24,R24))) -> 12057 | V24: Yes | W24: 2198 | X24: 172 | Y24: 15.4 | AB24: 7 | AC24: 5 | AD24: 460 | AE24: 5 Star (Global NCAP) | AF24: 6 | AG24: Yes | AH24: Yes | AI24: Yes | AJ24: Abyss Black | AK24: Fair | AL24: 145000 | AM24: 2027-11-03 | AN24: Telangana | AO24: Hyderabad | AP24: Reserved | AQ24: 2026-10-01 | AR24: Dealer | AS24: Yes | AT24: No | AU24: No | AV24: 4XPLOR Terrain Management, Body-on-Frame 4WD, Sony 3D Audio, Ventilated Seats | AW24: Well-maintained 2016 fair condition Mahindra Scorpio-N Z8L 2.2L mHawk 4XPLOR AT (Automatic) in Hyderabad. Powered by a 2198 cc diesel engine delivering 15.4 km/l. Complete service history available. | AX24: Enthusiast | AY24: 17100 | AZ24: Synthetic Sample
A25: CAR-1024 | B25: Mahindra | C25: Mahindra Thar ROXX | D25: Thar ROXX | E25: AX7L 2.2L mHawk 4WD AT | F25: 2026 | G25: 2026 | H25: New | I25: SUV | J25: Diesel | K25: Automatic | L25: 0 | M25: 2249000 | N25: 2250000 | O25: No | P25: 2249000 | Q25: 450000 | R25: =IF(V25="No",0,MAX(0,M25-Q25)) -> 1799000 | S25: 8.95 | T25: 84 | U25: =IF(OR(R25<=0,S25<0,T25<=0),"",IF(S25=0,R25/T25,-PMT(S25/1200,T25,R25))) -> 28899 | V25: Yes | W25: 2184 | X25: 172 | Y25: 15.2 | AB25: 5 | AC25: 5 | AD25: 447 | AE25: 5 Star (Bharat NCAP) | AF25: 6 | AG25: Yes | AH25: Yes | AI25: Yes | AJ25: Starry Night Blue | AK25: New | AL25: 38 | AM25: 2029-12-08 | AN25: Maharashtra | AO25: Mumbai | AP25: Sold | AQ25: 2026-09-04 | AR25: Dealer | AS25: Yes | AT25: Yes | AU25: No | AV25: 5-Door Off-Roader, CrawlSmart, IntelliTurn, Panoramic Skyroof, Harman Kardon 9-Speaker Audio | AW25: Brand-new 2026 showroom condition Mahindra Thar ROXX AX7L 2.2L mHawk 4WD AT (Automatic) in Mumbai. Powered by a 2184 cc diesel engine delivering 15.2 km/l. Complete service history available. | AX25: Enthusiast | AY25: 11800 | AZ25: Synthetic Sample
A26: CAR-1025 | B26: Mahindra | C26: Mahindra XUV 3XO | D26: XUV 3XO | E26: AX7L 1.2L TGDi AT | F26: 2023 | G26: 2023 | H26: Used | I26: SUV | J26: Petrol | K26: Automatic | L26: 1 | M26: 1065000 | N26: 1435000 | O26: No | P26: 1065000 | Q26: 265000 | R26: =IF(V26="No",0,MAX(0,M26-Q26)) -> 800000 | S26: 10.7 | T26: 36 | U26: =IF(OR(R26<=0,S26<0,T26<=0),"",IF(S26=0,R26/T26,-PMT(S26/1200,T26,R26))) -> 26077 | V26: Yes | W26: 1197 | X26: 129 | Y26: 18.2 | AB26: 5 | AC26: 5 | AD26: 364 | AE26: 5 Star (Bharat NCAP) | AF26: 6 | AG26: Yes | AH26: Yes | AI26: Yes | AJ26: Pearl Arctic White | AK26: Like New | AL26: 23900 | AM26: 2027-01-13 | AN26: Delhi | AO26: Delhi | AP26: Available | AQ26: 2026-10-07 | AR26: Individual | AS26: Yes | AT26: Yes | AU26: No | AV26: Segment-First Skyroof, Level 2 ADAS, Harman Kardon Audio with Amplifier, Dual-Zone AC | AW26: Well-maintained 2023 like new condition Mahindra XUV 3XO AX7L 1.2L TGDi AT (Automatic) in Delhi. Powered by a 1197 cc petrol engine delivering 18.2 km/l. Complete service history available. | AX26: Family | AY26: 9400 | AZ26: Synthetic Sample
A27: CAR-1026 | B27: Mahindra | C27: Mahindra BE 6 | D27: BE 6 | E27: Pack Three 79 kWh | F27: 2024 | G27: 2025 | H27: Used | I27: Coupe | J27: Electric | K27: Automatic | L27: 1 | M27: 2095000 | N27: 2555000 | O27: Yes | P27: 1990000 | Q27: 525000 | R27: =IF(V27="No",0,MAX(0,M27-Q27)) -> 1570000 | S27: 10.55 | T27: 48 | U27: =IF(OR(R27<=0,S27<0,T27<=0),"",IF(S27=0,R27/T27,-PMT(S27/1200,T27,R27))) -> 40235 | V27: Yes | X27: 282 | Z27: 682 | AA27: 79 | AB27: 5 | AC27: 5 | AD27: 455 | AE27: 5 Star (Bharat NCAP) | AF27: 7 | AG27: Yes | AH27: Yes | AI27: Yes | AJ27: Titan Grey | AK27: Like New | AL27: 22200 | AM27: 2026-12-18 | AN27: Maharashtra | AO27: Pune | AP27: Available | AQ27: 2026-09-10 | AR27: Dealer | AS27: Yes | AT27: Yes | AU27: No | AV27: INGLO Born Electric Platform, Infinity Roof, 16-Speaker Harman Kardon Dolby Atmos, AR HUD | AW27: Well-maintained 2024 like new condition Mahindra BE 6 Pack Three 79 kWh (Automatic) in Pune. Powered by a 79 kWh battery delivering 682 km certified range. Complete service history available. | AX27: Enthusiast | AY27: 6300 | AZ27: Synthetic Sample
A28: CAR-1027 | B28: Honda | C28: Honda City | D28: City | E28: ZX 1.5L i-VTEC CVT | F28: 2020 | G28: 2020 | H28: Used | I28: Sedan | J28: Petrol | K28: CVT | L28: 1 | M28: 765000 | N28: 1390000 | O28: Yes | P28: 735000 | Q28: 190000 | R28: =IF(V28="No",0,MAX(0,M28-Q28)) -> 575000 | S28: 11.15 | T28: 60 | U28: =IF(OR(R28<=0,S28<0,T28<=0),"",IF(S28=0,R28/T28,-PMT(S28/1200,T28,R28))) -> 12545 | V28: Yes | W28: 1498 | X28: 119 | Y28: 18.4 | AB28: 5 | AC28: 4 | AD28: 506 | AE28: 5 Star (ASEAN NCAP) | AF28: 6 | AG28: Yes | AH28: Yes | AI28: Yes | AJ28: Abyss Black | AK28: Excellent | AL28: 57400 | AM28: 2027-03-23 | AN28: Tamil Nadu | AO28: Coimbatore | AP28: Available | AQ28: 2026-10-13 | AR28: Dealer | AS28: Yes | AT28: No | AU28: No | AV28: Honda Sensing ADAS, LaneWatch Camera, Electric Sunroof, Walk Away Auto Lock | AW28: Well-maintained 2020 excellent condition Honda City ZX 1.5L i-VTEC CVT (CVT) in Coimbatore. Powered by a 1498 cc petrol engine delivering 18.4 km/l. Complete service history available. | AX28: Family | AY28: 10500 | AZ28: Synthetic Sample
A29: CAR-1028 | B29: Honda | C29: Honda City e:HEV | D29: City e:HEV | E29: ZX 1.5L Atkinson e-CVT | F29: 2015 | G29: 2015 | H29: Used | I29: Sedan | J29: Hybrid | K29: CVT | L29: 2 | M29: 450000 | N29: 1490000 | O29: No | P29: 450000 | Q29: 115000 | R29: =IF(V29="No",0,MAX(0,M29-Q29)) -> 0 | S29: 0 | T29: 0 | U29: =IF(OR(R29<=0,S29<0,T29<=0),"",IF(S29=0,R29/T29,-PMT(S29/1200,T29,R29))) | V29: No | W29: 1498 | X29: 124 | Y29: 27.13 | AB29: 5 | AC29: 4 | AD29: 410 | AE29: 5 Star (ASEAN NCAP) | AF29: 6 | AG29: Yes | AH29: Yes | AI29: Yes | AJ29: Starry Night Blue | AK29: Fair | AL29: 122400 | AM29: 2026-12-01 | AN29: Kerala | AO29: Kochi | AP29: Available | AQ29: 2026-09-16 | AR29: Individual | AS29: Yes | AT29: No | AU29: No | AV29: Self-Charging Strong Two-Motor Hybrid, Honda Sensing ADAS, Electronic Parking Brake | AW29: Well-maintained 2015 fair condition Honda City e:HEV ZX 1.5L Atkinson e-CVT (CVT) in Kochi. Powered by a 1498 cc hybrid engine delivering 27.13 km/l. Complete service history available. | AX29: Business | AY29: 13100 | AZ29: Synthetic Sample
A30: CAR-1029 | B30: Honda | C30: Honda Elevate | D30: Elevate | E30: ZX 1.5L i-VTEC CVT | F30: 2023 | G30: 2023 | H30: Used | I30: SUV | J30: Petrol | K30: CVT | L30: 1 | M30: 1125000 | N30: 1520000 | O30: Yes | P30: 1070000 | Q30: 280000 | R30: =IF(V30="No",0,MAX(0,M30-Q30)) -> 845000 | S30: 10.7 | T30: 48 | U30: =IF(OR(R30<=0,S30<0,T30<=0),"",IF(S30=0,R30/T30,-PMT(S30/1200,T30,R30))) -> 21717 | V30: Yes | W30: 1498 | X30: 119 | Y30: 16.92 | AB30: 5 | AC30: 5 | AD30: 458 | AF30: 6 | AG30: Yes | AH30: Yes | AI30: Yes | AJ30: Pearl Arctic White | AK30: Like New | AL30: 24200 | AM30: 2027-05-06 | AN30: Gujarat | AO30: Ahmedabad | AP30: Reserved | AQ30: 2026-10-19 | AR30: Dealer | AS30: No | AT30: Yes | AU30: No | AV30: 220mm Ground Clearance, Honda Sensing ADAS, 10.25-inch IPS HD Touchscreen, Sunroof | AW30: Well-maintained 2023 like new condition Honda Elevate ZX 1.5L i-VTEC CVT (CVT) in Ahmedabad. Powered by a 1498 cc petrol engine delivering 16.92 km/l. Inspected for mechanical reliability. | AX30: Family | AY30: 9600 | AZ30: Synthetic Sample
A31: CAR-1030 | B31: Honda | C31: Honda Amaze | D31: Amaze | E31: ZX 1.2L i-VTEC CVT | F31: 2017 | G31: 2017 | H31: Used | I31: Sedan | J31: Petrol | K31: CVT | L31: 2 | M31: 315000 | N31: 845000 | O31: Yes | P31: 300000 | Q31: 80000 | R31: =IF(V31="No",0,MAX(0,M31-Q31)) -> 235000 | S31: 11.6 | T31: 60 | U31: =IF(OR(R31<=0,S31<0,T31<=0),"",IF(S31=0,R31/T31,-PMT(S31/1200,T31,R31))) -> 5180 | V31: Yes | W31: 1199 | X31: 89 | Y31: 19.46 | AB31: 5 | AC31: 4 | AD31: 416 | AF31: 6 | AG31: Yes | AH31: Yes | AI31: Yes | AJ31: Titan Grey | AK31: Good | AL31: 87900 | AM31: 2026-12-11 | AN31: West Bengal | AO31: Kolkata | AP31: Sold | AQ31: 2026-09-22 | AR31: Dealer | AS31: Yes | AT31: No | AU31: No | AV31: Honda Sensing ADAS, LaneWatch Camera, Wireless Charger, Paddle Shifters | AW31: Well-maintained 2017 good condition Honda Amaze ZX 1.2L i-VTEC CVT (CVT) in Kolkata. Powered by a 1199 cc petrol engine delivering 19.46 km/l. Complete service history available. | AX31: First-Time Buyer | AY31: 9700 | AZ31: Synthetic Sample
A32: CAR-1031 | B32: Toyota | C32: Toyota Innova Hycross | D32: Innova Hycross | E32: ZX (O) 2.0L Strong Hybrid e-Drive | F32: 2025 | G32: 2026 | H32: Used | I32: MUV | J32: Hybrid | K32: CVT | L32: 1 | M32: 2735000 | N32: 3020000 | O32: No | P32: 2735000 | Q32: 685000 | R32: =IF(V32="No",0,MAX(0,M32-Q32)) -> 2050000 | S32: 10.4 | T32: 36 | U32: =IF(OR(R32<=0,S32<0,T32<=0),"",IF(S32=0,R32/T32,-PMT(S32/1200,T32,R32))) -> 66533 | V32: Yes | W32: 1987 | X32: 184 | Y32: 23.24 | AB32: 7 | AC32: 5 | AD32: 300 | AE32: 5 Star (Bharat NCAP) | AF32: 6 | AG32: Yes | AH32: Yes | AI32: Yes | AJ32: Abyss Black | AK32: Like New | AL32: 8100 | AM32: 2027-07-16 | AN32: Tamil Nadu | AO32: Chennai | AP32: Available | AQ32: 2026-10-03 | AR32: Individual | AS32: Yes | AT32: Yes | AU32: Unknown | AV32: Powered Ottoman 2nd Row Seats, Toyota Safety Sense ADAS, Panoramic Sunroof, JBL Audio | AW32: Well-maintained 2025 like new condition Toyota Innova Hycross ZX (O) 2.0L Strong Hybrid e-Drive (CVT) in Chennai. Powered by a 1987 cc hybrid engine delivering 23.24 km/l. Complete service history available. | AX32: Family | AY32: 10600 | AZ32: Synthetic Sample
A33: CAR-1032 | B33: Toyota | C33: Toyota Fortuner | D33: Fortuner | E33: Legender 2.8L 4x4 AT | F33: 2019 | G33: 2019 | H33: Used | I33: SUV | J33: Diesel | K33: Automatic | L33: 1 | M33: 1780000 | N33: 3930000 | O33: Yes | P33: 1690000 | Q33: 445000 | R33: =IF(V33="No",0,MAX(0,M33-Q33)) -> 1335000 | S33: 11.3 | T33: 48 | U33: =IF(OR(R33<=0,S33<0,T33<=0),"",IF(S33=0,R33/T33,-PMT(S33/1200,T33,R33))) -> 34699 | V33: Yes | W33: 2755 | X33: 201 | Y33: 14.2 | AB33: 7 | AC33: 5 | AD33: 296 | AE33: 5 Star (ASEAN NCAP) | AF33: 7 | AG33: Yes | AH33: Yes | AI33: Yes | AJ33: Starry Night Blue | AK33: Fair | AL33: 97000 | AM33: 2026-12-21 | AN33: Karnataka | AO33: Bengaluru | AP33: Available | AQ33: 2026-09-06 | AR33: Dealer | AS33: Yes | AT33: No | AU33: No | AV33: Quad-LED Headlamps, Active Traction Control (A-TRC), Kick-Sensor Powered Tailgate, JBL 11-Speaker | AW33: Well-maintained 2019 fair condition Toyota Fortuner Legender 2.8L 4x4 AT (Automatic) in Bengaluru. Powered by a 2755 cc diesel engine delivering 14.2 km/l. Complete service history available. | AX33: Business | AY33: 18600 | AZ33: Synthetic Sample
A34: CAR-1033 | B34: Toyota | C34: Toyota Urban Cruiser Hyryder | D34: Urban Cruiser Hyryder | E34: V 1.5L e-Drive Hybrid | F34: 2023 | G34: 2023 | H34: Used | I34: SUV | J34: Hybrid | K34: CVT | L34: 1 | M34: 1385000 | N34: 1870000 | O34: Yes | P34: 1330000 | Q34: 345000 | R34: =IF(V34="No",0,MAX(0,M34-Q34)) -> 1040000 | S34: 10.7 | T34: 60 | U34: =IF(OR(R34<=0,S34<0,T34<=0),"",IF(S34=0,R34/T34,-PMT(S34/1200,T34,R34))) -> 22457 | V34: Yes | W34: 1490 | X34: 114 | Y34: 27.97 | AB34: 5 | AC34: 5 | AD34: 265 | AF34: 6 | AG34: Yes | AH34: Yes | AI34: Yes | AJ34: Pearl Arctic White | AK34: Like New | AL34: 27600 | AM34: 2027-09-26 | AN34: Telangana | AO34: Hyderabad | AP34: Available | AQ34: 2026-10-09 | AR34: Dealer | AS34: Yes | AT34: Yes | AU34: No | AV34: Self-Charging Strong Hybrid, Panoramic Sunroof, Head-Up Display, Ventilated Leather Seats | AW34: Well-maintained 2023 like new condition Toyota Urban Cruiser Hyryder V 1.5L e-Drive Hybrid (CVT) in Hyderabad. Powered by a 1490 cc hybrid engine delivering 27.97 km/l. Complete service history available. | AX34: Family | AY34: 10000 | AZ34: Synthetic Sample
A35: CAR-1034 | B35: Toyota | C35: Toyota Glanza | D35: Glanza | E35: V 1.2L DualJet AMT | F35: 2021 | G35: 2021 | H35: Used | I35: Hatchback | J35: Petrol | K35: AMT | L35: 2 | M35: 530000 | N35: 875000 | O35: No | P35: 530000 | Q35: 135000 | R35: =IF(V35="No",0,MAX(0,M35-Q35)) -> 395000 | S35: 11 | T35: 36 | U35: =IF(OR(R35<=0,S35<0,T35<=0),"",IF(S35=0,R35/T35,-PMT(S35/1200,T35,R35))) -> 12932 | V35: Yes | W35: 1197 | X35: 89 | Y35: 22.94 | AB35: 5 | AC35: 5 | AD35: 318 | AF35: 6 | AG35: Yes | AH35: Yes | AI35: Yes | AJ35: Titan Grey | AK35: Excellent | AL35: 45500 | AM35: 2026-12-04 | AN35: Maharashtra | AO35: Mumbai | AP35: Available | AQ35: 2026-09-12 | AR35: Individual | AS35: Yes | AT35: No | AU35: No | AV35: 360 Degree Camera, HUD, 9-inch Smart Playcast, Toyota i-Connect | AW35: Well-maintained 2021 excellent condition Toyota Glanza V 1.2L DualJet AMT (AMT) in Mumbai. Powered by a 1197 cc petrol engine delivering 22.94 km/l. Complete service history available. | AX35: Daily Commuter | AY35: 7800 | AZ35: Synthetic Sample
A36: CAR-1035 | B36: Kia | C36: Kia Seltos | D36: Seltos | E36: GTX+ 1.5L Turbo GDi DCT | F36: 2016 | G36: 2016 | H36: Used | I36: SUV | J36: Petrol | K36: DCT | L36: 2 | M36: 510000 | N36: 1525000 | O36: Yes | P36: 485000 | Q36: 130000 | R36: =IF(V36="No",0,MAX(0,M36-Q36)) -> 380000 | S36: 11.75 | T36: 48 | U36: =IF(OR(R36<=0,S36<0,T36<=0),"",IF(S36=0,R36/T36,-PMT(S36/1200,T36,R36))) -> 9960 | V36: Yes | W36: 1482 | X36: 158 | Y36: 17.9 | AB36: 5 | AC36: 5 | AD36: 433 | AF36: 6 | AG36: Yes | AH36: Yes | AI36: Yes | AJ36: Abyss Black | AK36: Fair | AL36: 95600 | AM36: 2027-11-09 | AN36: Delhi | AO36: Delhi | AP36: Reserved | AQ36: 2026-10-15 | AR36: Dealer | AS36: Yes | AT36: No | AU36: No | AV36: ADAS Level 2 (19 Autonomous Features), Dual Pane Panoramic Sunroof, Bose 8-Speaker Audio | AW36: Well-maintained 2016 fair condition Kia Seltos GTX+ 1.5L Turbo GDi DCT (DCT) in Delhi. Powered by a 1482 cc petrol engine delivering 17.9 km/l. Complete service history available. | AX36: Family | AY36: 13900 | AZ36: Synthetic Sample
A37: CAR-1036 | B37: Kia | C37: Kia Sonet | D37: Sonet | E37: GTX+ 1.5L CRDi AT | F37: 2023 | G37: 2024 | H37: Used | I37: SUV | J37: Diesel | K37: Automatic | L37: 1 | M37: 1070000 | N37: 1445000 | O37: Yes | P37: 1025000 | Q37: 270000 | R37: =IF(V37="No",0,MAX(0,M37-Q37)) -> 800000 | S37: 10.7 | T37: 60 | U37: =IF(OR(R37<=0,S37<0,T37<=0),"",IF(S37=0,R37/T37,-PMT(S37/1200,T37,R37))) -> 17274 | V37: Yes | W37: 1493 | X37: 114 | Y37: 18.6 | AB37: 5 | AC37: 5 | AD37: 385 | AF37: 6 | AG37: Yes | AH37: Yes | AI37: Yes | AJ37: Starry Night Blue | AK37: Excellent | AL37: 36700 | AM37: 2026-12-14 | AN37: Maharashtra | AO37: Pune | AP37: Sold | AQ37: 2026-09-18 | AR37: Dealer | AS37: No | AT37: Yes | AU37: No | AV37: Level 1 ADAS, 360 Surround View Monitor, Ventilated Front Seats, Bose 7-Speaker System | AW37: Well-maintained 2023 excellent condition Kia Sonet GTX+ 1.5L CRDi AT (Automatic) in Pune. Powered by a 1493 cc diesel engine delivering 18.6 km/l. Inspected for mechanical reliability. | AX37: Daily Commuter | AY37: 9700 | AZ37: Synthetic Sample
A38: CAR-1037 | B38: Kia | C38: Kia Carens | D38: Carens | E38: Luxury Plus 1.5L Turbo DCT 7S | F38: 2018 | G38: 2018 | H38: Used | I38: MUV | J38: Petrol | K38: DCT | L38: 3 | M38: 635000 | N38: 1555000 | O38: No | P38: 635000 | Q38: 160000 | R38: =IF(V38="No",0,MAX(0,M38-Q38)) -> 475000 | S38: 11.45 | T38: 36 | U38: =IF(OR(R38<=0,S38<0,T38<=0),"",IF(S38=0,R38/T38,-PMT(S38/1200,T38,R38))) -> 15652 | V38: Yes | W38: 1482 | X38: 158 | Y38: 16.8 | AB38: 7 | AC38: 5 | AD38: 216 | AE38: 3 Star (Global NCAP) | AF38: 6 | AG38: Yes | AH38: Yes | AI38: Yes | AJ38: Pearl Arctic White | AK38: Fair | AL38: 95500 | AM38: 2027-01-19 | AN38: Tamil Nadu | AO38: Coimbatore | AP38: Available | AQ38: 2026-10-21 | AR38: Individual | AS38: Yes | AT38: No | AU38: No | AV38: One-Touch Easy Electric Tumble 2nd Row, SkyLight Sunroof, Ventilated Front Seats, 64-Colour Ambient Light | AW38: Well-maintained 2018 fair condition Kia Carens Luxury Plus 1.5L Turbo DCT 7S (DCT) in Coimbatore. Powered by a 1482 cc petrol engine delivering 16.8 km/l. Complete service history available. | AX38: Family | AY38: 12500 | AZ38: Synthetic Sample
A39: CAR-1038 | B39: Kia | C39: Kia EV6 | D39: EV6 | E39: GT Line AWD 77.4 kWh | F39: 2024 | G39: 2024 | H39: Used | I39: SUV | J39: Electric | K39: Automatic | L39: 1 | M39: 5130000 | N39: 6265000 | O39: Yes | P39: 4875000 | Q39: 1285000 | R39: =IF(V39="No",0,MAX(0,M39-Q39)) -> 3845000 | S39: 10.55 | T39: 48 | U39: =IF(OR(R39<=0,S39<0,T39<=0),"",IF(S39=0,R39/T39,-PMT(S39/1200,T39,R39))) -> 98538 | V39: Yes | X39: 321 | Z39: 708 | AA39: 77.4 | AB39: 5 | AC39: 5 | AD39: 490 | AE39: 5 Star (Euro NCAP) | AF39: 8 | AG39: Yes | AH39: Yes | AI39: Yes | AJ39: Titan Grey | AK39: Like New | AL39: 23500 | AM39: 2026-12-24 | AN39: Kerala | AO39: Kochi | AP39: Available | AQ39: 2026-09-02 | AR39: Dealer | AS39: Yes | AT39: Yes | AU39: No | AV39: Dual Motor All-Wheel Drive, 0-100 km/h in 5.2s, AR Head-Up Display, Meridian 14-Speaker Audio | AW39: Well-maintained 2024 like new condition Kia EV6 GT Line AWD 77.4 kWh (Automatic) in Kochi. Powered by a 77.4 kWh battery delivering 708 km certified range. Complete service history available. | AX39: Enthusiast | AY39: 7800 | AZ39: Synthetic Sample
A40: CAR-1039 | B40: Renault | C40: Renault Kiger | D40: Kiger | E40: RXZ 1.0L Turbo X-Tronic CVT | F40: 2020 | G40: 2020 | H40: Used | I40: SUV | J40: Petrol | K40: CVT | L40: 1 | M40: 525000 | N40: 955000 | O40: Yes | P40: 505000 | Q40: 130000 | R40: =IF(V40="No",0,MAX(0,M40-Q40)) -> 395000 | S40: 11.15 | T40: 60 | U40: =IF(OR(R40<=0,S40<0,T40<=0),"",IF(S40=0,R40/T40,-PMT(S40/1200,T40,R40))) -> 8618 | V40: Yes | W40: 999 | X40: 99 | Y40: 18.24 | AB40: 5 | AC40: 5 | AD40: 405 | AE40: 4 Star (Global NCAP) | AF40: 4 | AG40: Yes | AH40: Yes | AI40: Yes | AJ40: Abyss Black | AK40: Good | AL40: 71300 | AM40: 2027-03-02 | AN40: Gujarat | AO40: Ahmedabad | AP40: Available | AQ40: 2026-10-05 | AR40: Dealer | AS40: Yes | AT40: No | AU40: No | AV40: Multi-Sense Drive Modes, 3D Arkamys Sound System, Wireless Smartphone Replication, PM2.5 Filter | AW40: Well-maintained 2020 good condition Renault Kiger RXZ 1.0L Turbo X-Tronic CVT (CVT) in Ahmedabad. Powered by a 999 cc petrol engine delivering 18.24 km/l. Complete service history available. | AX40: First-Time Buyer | AY40: 8900 | AZ40: Synthetic Sample
A41: CAR-1040 | B41: Renault | C41: Renault Triber | D41: Triber | E41: RXZ 1.0L Easy-R AMT | F41: 2015 | G41: 2015 | H41: Used | I41: MUV | J41: Petrol | K41: AMT | L41: 2 | M41: 195000 | N41: 650000 | O41: No | P41: 195000 | Q41: 50000 | R41: =IF(V41="No",0,MAX(0,M41-Q41)) -> 0 | S41: 0 | T41: 0 | U41: =IF(OR(R41<=0,S41<0,T41<=0),"",IF(S41=0,R41/T41,-PMT(S41/1200,T41,R41))) | V41: No | W41: 999 | X41: 71 | Y41: 18.2 | AB41: 7 | AC41: 5 | AD41: 84 | AE41: 4 Star (Global NCAP) | AF41: 4 | AG41: Yes | AH41: Yes | AI41: Yes | AJ41: Starry Night Blue | AK41: Good | AL41: 92400 | AM41: 2026-12-07 | AN41: West Bengal | AO41: Kolkata | AP41: Available | AQ41: 2026-09-08 | AR41: Individual | AS41: Yes | AT41: No | AU41: No | AV41: Modular EasyFix 7-Seater (625L Boot in 5-Seater Mode), Twin AC with Vents on All Rows | AW41: Well-maintained 2015 good condition Renault Triber RXZ 1.0L Easy-R AMT (AMT) in Kolkata. Powered by a 999 cc petrol engine delivering 18.2 km/l. Complete service history available. | AX41: Family | AY41: 9800 | AZ41: Synthetic Sample
A42: CAR-1041 | B42: Renault | C42: Renault Kwid | D42: Kwid | E42: Climber 1.0L Easy-R AMT | F42: 2022 | G42: 2023 | H42: Used | I42: Hatchback | J42: Petrol | K42: AMT | L42: 1 | M42: 390000 | N42: 580000 | O42: Yes | P42: 370000 | Q42: 100000 | R42: =IF(V42="No",0,MAX(0,M42-Q42)) -> 290000 | S42: 10.85 | T42: 48 | U42: =IF(OR(R42<=0,S42<0,T42<=0),"",IF(S42=0,R42/T42,-PMT(S42/1200,T42,R42))) -> 7474 | V42: Yes | W42: 999 | X42: 67 | Y42: 22.3 | AB42: 5 | AC42: 5 | AD42: 279 | AF42: 2 | AG42: Yes | AH42: Yes | AI42: Yes | AJ42: Pearl Arctic White | AK42: Excellent | AL42: 31700 | AM42: 2027-05-12 | AN42: Tamil Nadu | AO42: Chennai | AP42: Reserved | AQ42: 2026-10-11 | AR42: Dealer | AS42: Yes | AT42: Yes | AU42: No | AV42: 8-inch MediaNAV Evolution Touchscreen, LED DRLs, Dual-Tone Climber Styling, ESP & Hill Start | AW42: Well-maintained 2022 excellent condition Renault Kwid Climber 1.0L Easy-R AMT (AMT) in Chennai. Powered by a 999 cc petrol engine delivering 22.3 km/l. Complete service history available. | AX42: First-Time Buyer | AY42: 6300 | AZ42: Synthetic Sample
A43: CAR-1042 | B43: Volkswagen | C43: Volkswagen Virtus | D43: Virtus | E43: GT Plus 1.5L TSI EVO DSG | F43: 2017 | G43: 2017 | H43: Used | I43: Sedan | J43: Petrol | K43: DCT | L43: 2 | M43: 615000 | N43: 1505000 | O43: Yes | P43: 590000 | Q43: 155000 | R43: =IF(V43="No",0,MAX(0,M43-Q43)) -> 460000 | S43: 11.6 | T43: 60 | U43: =IF(OR(R43<=0,S43<0,T43<=0),"",IF(S43=0,R43/T43,-PMT(S43/1200,T43,R43))) -> 10140 | V43: Yes | W43: 1498 | X43: 148 | Y43: 19.62 | AB43: 5 | AC43: 4 | AD43: 521 | AE43: 5 Star (Global NCAP) | AF43: 6 | AG43: Yes | AH43: Yes | AI43: Yes | AJ43: Titan Grey | AK43: Good | AL43: 69300 | AM43: 2026-12-17 | AN43: Karnataka | AO43: Bengaluru | AP43: Sold | AQ43: 2026-09-14 | AR43: Dealer | AS43: Yes | AT43: No | AU43: No | AV43: Active Cylinder Technology (ACT), 7-Speed DSG, Electric Front Seats, Red GT Calipers | AW43: Well-maintained 2017 good condition Volkswagen Virtus GT Plus 1.5L TSI EVO DSG (DCT) in Bengaluru. Powered by a 1498 cc petrol engine delivering 19.62 km/l. Complete service history available. | AX43: Enthusiast | AY43: 14700 | AZ43: Synthetic Sample
A44: CAR-1043 | B44: Volkswagen | C44: Volkswagen Taigun | D44: Taigun | E44: GT Plus Chrome 1.5L TSI DSG | F44: 2024 | G44: 2024 | H44: Used | I44: SUV | J44: Petrol | K44: DCT | L44: 1 | M44: 1535000 | N44: 1875000 | O44: No | P44: 1535000 | Q44: 385000 | R44: =IF(V44="No",0,MAX(0,M44-Q44)) -> 1150000 | S44: 10.55 | T44: 36 | U44: =IF(OR(R44<=0,S44<0,T44<=0),"",IF(S44=0,R44/T44,-PMT(S44/1200,T44,R44))) -> 37405 | V44: Yes | W44: 1498 | X44: 148 | Y44: 19.01 | AB44: 5 | AC44: 5 | AD44: 385 | AE44: 5 Star (Global NCAP) | AF44: 6 | AG44: Yes | AH44: Yes | AI44: Yes | AJ44: Abyss Black | AK44: Like New | AL44: 18600 | AM44: 2027-07-22 | AN44: Telangana | AO44: Hyderabad | AP44: Available | AQ44: 2026-10-17 | AR44: Individual | AS44: No | AT44: Yes | AU44: No | AV44: 1.5L TSI EVO with Cylinder Deactivation, Ventilated Leather Seats, Infinity LED Tail Lamps | AW44: Well-maintained 2024 like new condition Volkswagen Taigun GT Plus Chrome 1.5L TSI DSG (DCT) in Hyderabad. Powered by a 1498 cc petrol engine delivering 19.01 km/l. Inspected for mechanical reliability. | AX44: Enthusiast | AY44: 11900 | AZ44: Synthetic Sample
A45: CAR-1044 | B45: Skoda | C45: Skoda Slavia | D45: Slavia | E45: Prestige 1.5L TSI DSG | F45: 2019 | G45: 2019 | H45: Used | I45: Sedan | J45: Petrol | K45: DCT | L45: 1 | M45: 765000 | N45: 1540000 | O45: Yes | P45: 725000 | Q45: 190000 | R45: =IF(V45="No",0,MAX(0,M45-Q45)) -> 575000 | S45: 11.3 | T45: 48 | U45: =IF(OR(R45<=0,S45<0,T45<=0),"",IF(S45=0,R45/T45,-PMT(S45/1200,T45,R45))) -> 14945 | V45: Yes | W45: 1498 | X45: 148 | Y45: 19.36 | AB45: 5 | AC45: 4 | AD45: 521 | AE45: 5 Star (Global NCAP) | AF45: 6 | AG45: Yes | AH45: Yes | AI45: Yes | AJ45: Starry Night Blue | AK45: Good | AL45: 54200 | AM45: 2026-12-27 | AN45: Maharashtra | AO45: Mumbai | AP45: Available | AQ45: 2026-09-20 | AR45: Dealer | AS45: Yes | AT45: No | AU45: No | AV45: 10-inch Skoda Play Infotainment, Subwoofer in Boot, Electric Sunroof, Ventilated Powered Seats | AW45: Well-maintained 2019 good condition Skoda Slavia Prestige 1.5L TSI DSG (DCT) in Mumbai. Powered by a 1498 cc petrol engine delivering 19.36 km/l. Complete service history available. | AX45: Enthusiast | AY45: 13600 | AZ45: Synthetic Sample
A46: CAR-1045 | B46: Skoda | C46: Skoda Kushaq | D46: Kushaq | E46: Monte Carlo 1.5L TSI DSG | F46: 2026 | G46: 2026 | H46: New | I46: SUV | J46: Petrol | K46: DCT | L46: 0 | M46: 2049000 | N46: 2050000 | O46: Yes | P46: 1965000 | Q46: 410000 | R46: =IF(V46="No",0,MAX(0,M46-Q46)) -> 1639000 | S46: 8.95 | T46: 84 | U46: =IF(OR(R46<=0,S46<0,T46<=0),"",IF(S46=0,R46/T46,-PMT(S46/1200,T46,R46))) -> 26328 | V46: Yes | W46: 1498 | X46: 148 | Y46: 18.86 | AB46: 5 | AC46: 5 | AD46: 385 | AE46: 5 Star (Global NCAP) | AF46: 6 | AG46: Yes | AH46: Yes | AI46: Yes | AJ46: Pearl Arctic White | AK46: New | AL46: 59 | AM46: 2029-09-05 | AN46: Delhi | AO46: Delhi | AP46: Available | AQ46: 2026-10-01 | AR46: Dealer | AS46: Yes | AT46: Yes | AU46: No | AV46: Monte Carlo Ruby Red & Black Cockpit, Virtual Cockpit, Simply Clever Umbrella Holder | AW46: Brand-new 2026 showroom condition Skoda Kushaq Monte Carlo 1.5L TSI DSG (DCT) in Delhi. Powered by a 1498 cc petrol engine delivering 18.86 km/l. Complete service history available. | AX46: Enthusiast | AY46: 10900 | AZ46: Synthetic Sample
A47: CAR-1046 | B47: Skoda | C47: Skoda Kylaq | D47: Kylaq | E47: Prestige 1.0L TSI AT | F47: 2024 | G47: 2025 | H47: Used | I47: SUV | J47: Petrol | K47: Automatic | L47: 1 | M47: 1120000 | N47: 1370000 | O47: No | P47: 1120000 | Q47: 280000 | R47: =IF(V47="No",0,MAX(0,M47-Q47)) -> 840000 | S47: 10.55 | T47: 36 | U47: =IF(OR(R47<=0,S47<0,T47<=0),"",IF(S47=0,R47/T47,-PMT(S47/1200,T47,R47))) -> 27322 | V47: Yes | W47: 999 | X47: 114 | Y47: 19.05 | AB47: 5 | AC47: 5 | AD47: 446 | AE47: 5 Star (Bharat NCAP) | AF47: 6 | AG47: Yes | AH47: Yes | AI47: Yes | AJ47: Titan Grey | AK47: Like New | AL47: 23000 | AM47: 2026-12-10 | AN47: Maharashtra | AO47: Pune | AP47: Available | AQ47: 2026-09-04 | AR47: Individual | AS47: Yes | AT47: Yes | AU47: Unknown | AV47: MQB-A0-IN Platform, 6-Way Powered & Ventilated Front Seats, Electric Sunroof, 25+ Active Safety Features | AW47: Well-maintained 2024 like new condition Skoda Kylaq Prestige 1.0L TSI AT (Automatic) in Pune. Powered by a 999 cc petrol engine delivering 19.05 km/l. Complete service history available. | AX47: Family | AY47: 9500 | AZ47: Synthetic Sample
A48: CAR-1047 | B48: MG | C48: MG Hector | D48: Hector | E48: Sharp Pro 1.5L Turbo CVT | F48: 2016 | G48: 2016 | H48: Used | I48: SUV | J48: Petrol | K48: CVT | L48: 2 | M48: 545000 | N48: 1630000 | O48: Yes | P48: 520000 | Q48: 135000 | R48: =IF(V48="No",0,MAX(0,M48-Q48)) -> 410000 | S48: 11.75 | T48: 48 | U48: =IF(OR(R48<=0,S48<0,T48<=0),"",IF(S48=0,R48/T48,-PMT(S48/1200,T48,R48))) -> 10747 | V48: Yes | W48: 1451 | X48: 141 | Y48: 13.79 | AB48: 5 | AC48: 5 | AD48: 587 | AF48: 6 | AG48: Yes | AH48: Yes | AI48: Yes | AJ48: Abyss Black | AK48: Fair | AL48: 97500 | AM48: 2027-11-15 | AN48: Tamil Nadu | AO48: Coimbatore | AP48: Reserved | AQ48: 2026-10-07 | AR48: Dealer | AS48: Yes | AT48: No | AU48: No | AV48: 14-inch HD Portrait Infotainment, Dual-Pane Panoramic Sunroof, Level 2 ADAS, Digital Bluetooth Key | AW48: Well-maintained 2016 fair condition MG Hector Sharp Pro 1.5L Turbo CVT (CVT) in Coimbatore. Powered by a 1451 cc petrol engine delivering 13.79 km/l. Complete service history available. | AX48: Family | AY48: 15700 | AZ48: Synthetic Sample
A49: CAR-1048 | B49: MG | C49: MG Windsor EV | D49: Windsor EV | E49: Essence 38 kWh | F49: 2026 | G49: 2026 | H49: New | I49: MUV | J49: Electric | K49: Automatic | L49: 0 | M49: 1550000 | N49: 1550000 | O49: No | P49: 1550000 | Q49: 310000 | R49: =IF(V49="No",0,MAX(0,M49-Q49)) -> 1240000 | S49: 8.65 | T49: 84 | U49: =IF(OR(R49<=0,S49<0,T49<=0),"",IF(S49=0,R49/T49,-PMT(S49/1200,T49,R49))) -> 19731 | V49: Yes | X49: 134 | Z49: 332 | AA49: 38 | AB49: 5 | AC49: 5 | AD49: 604 | AF49: 6 | AG49: Yes | AH49: Yes | AI49: Yes | AJ49: Starry Night Blue | AK49: New | AL49: 17 | AM49: 2029-12-20 | AN49: Kerala | AO49: Kochi | AP49: Sold | AQ49: 2026-09-10 | AR49: Dealer | AS49: Yes | AT49: Yes | AU49: No | AV49: 135-Degree Aero Lounge Reclining Seats, Infinity View Glass Roof, 15.6-inch GrandView Touch Display | AW49: Brand-new 2026 showroom condition MG Windsor EV Essence 38 kWh (Automatic) in Kochi. Powered by a 38 kWh battery delivering 332 km certified range. Complete service history available. | AX49: Family | AY49: 4900 | AZ49: Synthetic Sample
A50: CAR-1049 | B50: MG | C50: MG ZS EV | D50: ZS EV | E50: Exclusive Plus 50.3 kWh | F50: 2021 | G50: 2021 | H50: Used | I50: SUV | J50: Electric | K50: Automatic | L50: 2 | M50: 1350000 | N50: 2225000 | O50: No | P50: 1350000 | Q50: 340000 | R50: =IF(V50="No",0,MAX(0,M50-Q50)) -> 1010000 | S50: 11 | T50: 36 | U50: =IF(OR(R50<=0,S50<0,T50<=0),"",IF(S50=0,R50/T50,-PMT(S50/1200,T50,R50))) -> 33066 | V50: Yes | X50: 174 | Z50: 461 | AA50: 50.3 | AB50: 5 | AC50: 5 | AD50: 448 | AE50: 5 Star (Euro NCAP) | AF50: 6 | AG50: Yes | AH50: Yes | AI50: Yes | AJ50: Pearl Arctic White | AK50: Excellent | AL50: 54400 | AM50: 2027-01-25 | AN50: Gujarat | AO50: Ahmedabad | AP50: Available | AQ50: 2026-10-13 | AR50: Individual | AS50: Yes | AT50: No | AU50: No | AV50: Level 2 ADAS, Panoramic Sky Roof, i-SMART 75+ Connected Features, PM2.5 Filter | AW50: Well-maintained 2021 excellent condition MG ZS EV Exclusive Plus 50.3 kWh (Automatic) in Ahmedabad. Powered by a 50.3 kWh battery delivering 461 km certified range. Complete service history available. | AX50: Family | AY50: 6500 | AZ50: Synthetic Sample
A51: CAR-1050 | B51: BYD | C51: BYD Atto 3 | D51: Atto 3 | E51: Superior 60.48 kWh Blade Battery | F51: 2024 | G51: 2024 | H51: Used | I51: SUV | J51: Electric | K51: Automatic | L51: 1 | M51: 2645000 | N51: 3230000 | O51: Yes | P51: 2515000 | Q51: 660000 | R51: =IF(V51="No",0,MAX(0,M51-Q51)) -> 1985000 | S51: 10.55 | T51: 48 | U51: =IF(OR(R51<=0,S51<0,T51<=0),"",IF(S51=0,R51/T51,-PMT(S51/1200,T51,R51))) -> 50871 | V51: Yes | X51: 201 | Z51: 521 | AA51: 60.48 | AB51: 5 | AC51: 5 | AD51: 440 | AE51: 5 Star (Euro NCAP) | AF51: 7 | AG51: Yes | AH51: Yes | AI51: Yes | AJ51: Titan Grey | AK51: Like New | AL51: 23200 | AM51: 2026-12-03 | AN51: West Bengal | AO51: Kolkata | AP51: Available | AQ51: 2026-09-16 | AR51: Dealer | AS51: No | AT51: Yes | AU51: No | AV51: BYD Blade Battery, 12.8-inch Rotating Touchscreen, Level 2 ADAS, NFC Card Key | AW51: Well-maintained 2024 like new condition BYD Atto 3 Superior 60.48 kWh Blade Battery (Automatic) in Kolkata. Powered by a 60.48 kWh battery delivering 521 km certified range. Inspected for mechanical reliability. | AX51: Family | AY51: 6600 | AZ51: Synthetic Sample
A52: CAR-1051 | B52: BYD | C52: BYD Seal | D52: Seal | E52: Premium 82.56 kWh Extended Range | F52: 2025 | G52: 2026 | H52: Used | I52: Sedan | J52: Electric | K52: Automatic | L52: 1 | M52: 4020000 | N52: 4440000 | O52: Yes | P52: 3860000 | Q52: 1005000 | R52: =IF(V52="No",0,MAX(0,M52-Q52)) -> 3015000 | S52: 10.4 | T52: 60 | U52: =IF(OR(R52<=0,S52<0,T52<=0),"",IF(S52=0,R52/T52,-PMT(S52/1200,T52,R52))) -> 64655 | V52: Yes | X52: 308 | Z52: 650 | AA52: 82.56 | AB52: 5 | AC52: 4 | AD52: 400 | AE52: 5 Star (Euro NCAP) | AF52: 9 | AG52: Yes | AH52: Yes | AI52: Yes | AJ52: Abyss Black | AK52: Like New | AL52: 11600 | AM52: 2027-03-08 | AN52: Tamil Nadu | AO52: Chennai | AP52: Available | AQ52: 2026-10-19 | AR52: Dealer | AS52: Yes | AT52: Yes | AU52: No | AV52: Cell-to-Body (CTB) Technology, 15.6-inch Rotating Screen, Dynaudio 12-Speaker Sound, Panoramic Silver-Plated Glass Roof | AW52: Well-maintained 2025 like new condition BYD Seal Premium 82.56 kWh Extended Range (Automatic) in Chennai. Powered by a 82.56 kWh battery delivering 650 km certified range. Complete service history available. | AX52: Enthusiast | AY52: 7100 | AZ52: Synthetic Sample
A53: CAR-1052 | B53: BMW | C53: BMW 3 Series Gran Limousine | D53: 3 Series Gran Limousine | E53: 330Li M Sport | F53: 2015 | G53: 2015 | H53: Used | I53: Luxury | J53: Petrol | K53: Automatic | L53: 2 | M53: 1120000 | N53: 4395000 | O53: No | P53: 1120000 | Q53: 280000 | R53: =IF(V53="No",0,MAX(0,M53-Q53)) -> 0 | S53: 0 | T53: 0 | U53: =IF(OR(R53<=0,S53<0,T53<=0),"",IF(S53=0,R53/T53,-PMT(S53/1200,T53,R53))) | V53: No | W53: 1998 | X53: 255 | Y53: 15.39 | AB53: 5 | AC53: 4 | AD53: 480 | AE53: 5 Star (Euro NCAP) | AF53: 6 | AG53: Yes | AH53: Yes | AI53: Yes | AJ53: Starry Night Blue | AK53: Fair | AL53: 111700 | AM53: 2026-12-13 | AN53: Karnataka | AO53: Bengaluru | AP53: Available | AQ53: 2026-09-22 | AR53: Individual | AS53: Yes | AT53: No | AU53: No | AV53: Extended 2,961mm Wheelbase, BMW Curved Display iDrive 8, Harman Kardon 16-Speaker Surround, Panoramic Sunroof | AW53: Well-maintained 2015 fair condition BMW 3 Series Gran Limousine 330Li M Sport (Automatic) in Bengaluru. Powered by a 1998 cc petrol engine delivering 15.39 km/l. Complete service history available. | AX53: Business | AY53: 54700 | AZ53: Synthetic Sample
A54: CAR-1053 | B54: BMW | C54: BMW X1 | D54: X1 | E54: sDrive18d M Sport | F54: 2022 | G54: 2022 | H54: Used | I54: Luxury | J54: Diesel | K54: DCT | L54: 1 | M54: 2710000 | N54: 4840000 | O54: Yes | P54: 2575000 | Q54: 680000 | R54: =IF(V54="No",0,MAX(0,M54-Q54)) -> 2030000 | S54: 10.85 | T54: 48 | U54: =IF(OR(R54<=0,S54<0,T54<=0),"",IF(S54=0,R54/T54,-PMT(S54/1200,T54,R54))) -> 52319 | V54: Yes | W54: 1995 | X54: 148 | Y54: 20.37 | AB54: 5 | AC54: 5 | AD54: 476 | AE54: 5 Star (Euro NCAP) | AF54: 6 | AG54: Yes | AH54: Yes | AI54: Yes | AJ54: Pearl Arctic White | AK54: Excellent | AL54: 59200 | AM54: 2027-05-18 | AN54: Telangana | AO54: Hyderabad | AP54: Reserved | AQ54: 2026-10-03 | AR54: Dealer | AS54: Yes | AT54: Yes | AU54: No | AV54: Active Front Seats with Massage Function, Adaptive LED Headlights, Harman Kardon 12-Speaker System | AW54: Well-maintained 2022 excellent condition BMW X1 sDrive18d M Sport (DCT) in Hyderabad. Powered by a 1995 cc diesel engine delivering 20.37 km/l. Complete service history available. | AX54: Business | AY54: 40600 | AZ54: Synthetic Sample
A55: CAR-1054 | B55: BMW | C55: BMW iX1 | D55: iX1 | E55: xDrive30 M Sport 66.4 kWh | F55: 2024 | G55: 2024 | H55: Used | I55: Luxury | J55: Electric | K55: Automatic | L55: 1 | M55: 4755000 | N55: 6355000 | O55: Yes | P55: 4565000 | Q55: 1190000 | R55: =IF(V55="No",0,MAX(0,M55-Q55)) -> 3565000 | S55: 10.55 | T55: 60 | U55: =IF(OR(R55<=0,S55<0,T55<=0),"",IF(S55=0,R55/T55,-PMT(S55/1200,T55,R55))) -> 76714 | V55: Yes | X55: 308 | Z55: 440 | AA55: 66.4 | AB55: 5 | AC55: 5 | AD55: 490 | AE55: 5 Star (Euro NCAP) | AF55: 6 | AG55: Yes | AH55: Yes | AI55: Yes | AJ55: Titan Grey | AK55: Like New | AL55: 22000 | AM55: 2026-12-23 | AN55: Maharashtra | AO55: Mumbai | AP55: Sold | AQ55: 2026-09-06 | AR55: Dealer | AS55: Yes | AT55: Yes | AU55: No | AV55: Dual-Motor xDrive All-Wheel Drive, Adaptive M Suspension, BMW Curved Display, Reversing Assistant | AW55: Well-maintained 2024 like new condition BMW iX1 xDrive30 M Sport 66.4 kWh (Automatic) in Mumbai. Powered by a 66.4 kWh battery delivering 440 km certified range. Complete service history available. | AX55: Business | AY55: 23800 | AZ55: Synthetic Sample
A56: CAR-1055 | B56: Mercedes-Benz | C56: Mercedes-Benz C-Class | D56: C-Class | E56: C 200 Avantgarde | F56: 2024 | G56: 2024 | H56: Used | I56: Luxury | J56: Petrol | K56: Automatic | L56: 1 | M56: 4395000 | N56: 5875000 | O56: No | P56: 4395000 | Q56: 1100000 | R56: =IF(V56="No",0,MAX(0,M56-Q56)) -> 3295000 | S56: 10.55 | T56: 36 | U56: =IF(OR(R56<=0,S56<0,T56<=0),"",IF(S56=0,R56/T56,-PMT(S56/1200,T56,R56))) -> 107173 | V56: Yes | W56: 1496 | X56: 201 | Y56: 16.9 | AB56: 5 | AC56: 4 | AD56: 455 | AE56: 5 Star (Euro NCAP) | AF56: 7 | AG56: Yes | AH56: Yes | AI56: Yes | AJ56: Abyss Black | AK56: Like New | AL56: 24100 | AM56: 2027-07-01 | AN56: Delhi | AO56: Delhi | AP56: Available | AQ56: 2026-10-09 | AR56: Individual | AS56: Yes | AT56: Yes | AU56: No | AV56: 11.9-inch Portrait MBUX Gen 2 Touchscreen, 48V Integrated Starter Generator, Burmester 3D Surround | AW56: Well-maintained 2024 like new condition Mercedes-Benz C-Class C 200 Avantgarde (Automatic) in Delhi. Powered by a 1496 cc petrol engine delivering 16.9 km/l. Complete service history available. | AX56: Business | AY56: 45400 | AZ56: Synthetic Sample
A57: CAR-1056 | B57: Mercedes-Benz | C57: Mercedes-Benz GLC | D57: GLC | E57: 300 4MATIC | F57: 2019 | G57: 2020 | H57: Used | I57: Luxury | J57: Petrol | K57: Automatic | L57: 1 | M57: 2270000 | N57: 6260000 | O57: Yes | P57: 2155000 | Q57: 570000 | R57: =IF(V57="No",0,MAX(0,M57-Q57)) -> 1700000 | S57: 11.3 | T57: 48 | U57: =IF(OR(R57<=0,S57<0,T57<=0),"",IF(S57=0,R57/T57,-PMT(S57/1200,T57,R57))) -> 44185 | V57: Yes | W57: 1999 | X57: 255 | Y57: 14.72 | AB57: 5 | AC57: 5 | AD57: 620 | AE57: 5 Star (Euro NCAP) | AF57: 7 | AG57: Yes | AH57: Yes | AI57: Yes | AJ57: Starry Night Blue | AK57: Good | AL57: 72600 | AM57: 2026-12-06 | AN57: Maharashtra | AO57: Pune | AP57: Available | AQ57: 2026-09-12 | AR57: Dealer | AS57: Yes | AT57: No | AU57: No | AV57: Transparent Bonnet Off-Road View, 4MATIC All-Wheel Drive, Burmester 15-Speaker 710W Sound | AW57: Well-maintained 2019 good condition Mercedes-Benz GLC 300 4MATIC (Automatic) in Pune. Powered by a 1999 cc petrol engine delivering 14.72 km/l. Complete service history available. | AX57: Business | AY57: 58900 | AZ57: Synthetic Sample
A58: CAR-1057 | B58: Mercedes-Benz | C58: Mercedes-Benz EQA | D58: EQA | E58: 250+ 70.5 kWh | F58: 2023 | G58: 2023 | H58: Used | I58: Luxury | J58: Electric | K58: Automatic | L58: 1 | M58: 3950000 | N58: 6105000 | O58: Yes | P58: 3790000 | Q58: 990000 | R58: =IF(V58="No",0,MAX(0,M58-Q58)) -> 2960000 | S58: 10.7 | T58: 60 | U58: =IF(OR(R58<=0,S58<0,T58<=0),"",IF(S58=0,R58/T58,-PMT(S58/1200,T58,R58))) -> 63916 | V58: Yes | X58: 188 | Z58: 560 | AA58: 70.5 | AB58: 5 | AC58: 5 | AD58: 340 | AE58: 5 Star (Euro NCAP) | AF58: 7 | AG58: Yes | AH58: Yes | AI58: Yes | AJ58: Pearl Arctic White | AK58: Excellent | AL58: 33900 | AM58: 2027-09-11 | AN58: Tamil Nadu | AO58: Coimbatore | AP58: Available | AQ58: 2026-10-15 | AR58: Dealer | AS58: No | AT58: Yes | AU58: No | AV58: Burmester Surround with Dolby Atmos, Augmented Reality Navigation, Blind Spot Assist, Gesture Control | AW58: Well-maintained 2023 excellent condition Mercedes-Benz EQA 250+ 70.5 kWh (Automatic) in Coimbatore. Powered by a 70.5 kWh battery delivering 560 km certified range. Inspected for mechanical reliability. | AX58: Business | AY58: 26900 | AZ58: Synthetic Sample
A59: CAR-1058 | B59: Audi | C59: Audi A4 | D59: A4 | E59: Technology 40 TFSI | F59: 2021 | G59: 2021 | H59: Used | I59: Luxury | J59: Petrol | K59: DCT | L59: 2 | M59: 2310000 | N59: 4770000 | O59: No | P59: 2310000 | Q59: 580000 | R59: =IF(V59="No",0,MAX(0,M59-Q59)) -> 1730000 | S59: 11 | T59: 36 | U59: =IF(OR(R59<=0,S59<0,T59<=0),"",IF(S59=0,R59/T59,-PMT(S59/1200,T59,R59))) -> 56638 | V59: Yes | W59: 1984 | X59: 201 | Y59: 17.4 | AB59: 5 | AC59: 4 | AD59: 460 | AE59: 5 Star (Euro NCAP) | AF59: 8 | AG59: Yes | AH59: Yes | AI59: Yes | AJ59: Titan Grey | AK59: Excellent | AL59: 44200 | AM59: 2026-12-16 | AN59: Kerala | AO59: Kochi | AP59: Available | AQ59: 2026-09-18 | AR59: Individual | AS59: Yes | AT59: No | AU59: No | AV59: Audi Virtual Cockpit Plus, Bang & Olufsen 19-Speaker 3D Sound, Matrix LED Headlights, Park Assist | AW59: Well-maintained 2021 excellent condition Audi A4 Technology 40 TFSI (DCT) in Kochi. Powered by a 1984 cc petrol engine delivering 17.4 km/l. Complete service history available. | AX59: Business | AY59: 46800 | AZ59: Synthetic Sample
A60: CAR-1059 | B60: Audi | C60: Audi Q3 | D60: Q3 | E60: Technology 40 TFSI quattro | F60: 2016 | G60: 2016 | H60: Used | I60: Luxury | J60: Petrol | K60: DCT | L60: 2 | M60: 1045000 | N60: 4100000 | O60: Yes | P60: 995000 | Q60: 260000 | R60: =IF(V60="No",0,MAX(0,M60-Q60)) -> 785000 | S60: 11.75 | T60: 48 | U60: =IF(OR(R60<=0,S60<0,T60<=0),"",IF(S60=0,R60/T60,-PMT(S60/1200,T60,R60))) -> 20576 | V60: Yes | W60: 1984 | X60: 187 | Y60: 14.93 | AB60: 5 | AC60: 5 | AD60: 530 | AE60: 5 Star (Euro NCAP) | AF60: 6 | AG60: Yes | AH60: Yes | AI60: Yes | AJ60: Abyss Black | AK60: Fair | AL60: 99000 | AM60: 2027-11-21 | AN60: Gujarat | AO60: Ahmedabad | AP60: Reserved | AQ60: 2026-10-21 | AR60: Dealer | AS60: Yes | AT60: No | AU60: No | AV60: quattro Permanent All-Wheel Drive, Panoramic Glass Sunroof, Gesture Controlled Tailgate, 30-Colour Ambient Light | AW60: Well-maintained 2016 fair condition Audi Q3 Technology 40 TFSI quattro (DCT) in Ahmedabad. Powered by a 1984 cc petrol engine delivering 14.93 km/l. Complete service history available. | AX60: Business | AY60: 57400 | AZ60: Synthetic Sample
A61: CAR-1060 | B61: Audi | C61: Audi Q8 e-tron | D61: Q8 e-tron | E61: 55 quattro 114 kWh | F61: 2026 | G61: 2026 | H61: New | I61: Luxury | J61: Electric | K61: Automatic | L61: 0 | M61: 12700000 | N61: 12700000 | O61: No | P61: 12700000 | Q61: 2540000 | R61: =IF(V61="No",0,MAX(0,M61-Q61)) -> 10160000 | S61: 8.65 | T61: 84 | U61: =IF(OR(R61<=0,S61<0,T61<=0),"",IF(S61=0,R61/T61,-PMT(S61/1200,T61,R61))) -> 161666 | V61: Yes | X61: 402 | Z61: 582 | AA61: 114 | AB61: 5 | AC61: 5 | AD61: 569 | AE61: 5 Star (Euro NCAP) | AF61: 8 | AG61: Yes | AH61: Yes | AI61: Yes | AJ61: Starry Night Blue | AK61: New | AL61: 29 | AM61: 2029-12-26 | AN61: West Bengal | AO61: Kolkata | AP61: Sold | AQ61: 2026-09-02 | AR61: Dealer | AS61: Yes | AT61: Yes | AU61: No | AV61: Adaptive Air Suspension, Dual quattro Electric Motors, 170 kW DC Fast Charging, Digital Matrix LED | AW61: Brand-new 2026 showroom condition Audi Q8 e-tron 55 quattro 114 kWh (Automatic) in Kolkata. Powered by a 114 kWh battery delivering 582 km certified range. Complete service history available. | AX61: Business | AY61: 29000 | AZ61: Synthetic Sample
A62: CAR-1061 | B62: Jeep | C62: Jeep Compass | D62: Compass | E62: Model S (O) 2.0L Multijet II 4x4 AT | F62: 2018 | G62: 2019 | H62: Used | I62: SUV | J62: Diesel | K62: Automatic | L62: 3 | M62: 1065000 | N62: 2595000 | O62: No | P62: 1065000 | Q62: 265000 | R62: =IF(V62="No",0,MAX(0,M62-Q62)) -> 800000 | S62: 11.45 | T62: 36 | U62: =IF(OR(R62<=0,S62<0,T62<=0),"",IF(S62=0,R62/T62,-PMT(S62/1200,T62,R62))) -> 26362 | V62: Yes | W62: 1956 | X62: 168 | Y62: 14.9 | AB62: 5 | AC62: 5 | AD62: 438 | AE62: 5 Star (Euro NCAP) | AF62: 6 | AG62: Yes | AH62: Yes | AI62: Yes | AJ62: Pearl Arctic White | AK62: Fair | AL62: 111600 | AM62: 2027-01-04 | AN62: Tamil Nadu | AO62: Chennai | AP62: Available | AQ62: 2026-10-05 | AR62: Individual | AS62: Yes | AT62: No | AU62: Unknown | AV62: Jeep Active Drive 4x4 Selec-Terrain, 9-Speed Automatic, Ventilated Leather Seats, Alpine 9-Speaker Audio | AW62: Well-maintained 2018 fair condition Jeep Compass Model S (O) 2.0L Multijet II 4x4 AT (Automatic) in Chennai. Powered by a 1956 cc diesel engine delivering 14.9 km/l. Complete service history available. | AX62: Enthusiast | AY62: 20500 | AZ62: Synthetic Sample
A63: CAR-1062 | B63: Maruti Suzuki | C63: Maruti Suzuki Swift | D63: Swift | E63: ZXi+ 1.2L DualJet | F63: 2025 | G63: 2025 | H63: Used | I63: Hatchback | J63: Petrol | K63: Manual | L63: 1 | M63: 790000 | N63: 875000 | O63: Yes | P63: 750000 | Q63: 200000 | R63: =IF(V63="No",0,MAX(0,M63-Q63)) -> 590000 | S63: 10.4 | T63: 48 | U63: =IF(OR(R63<=0,S63<0,T63<=0),"",IF(S63=0,R63/T63,-PMT(S63/1200,T63,R63))) -> 15078 | V63: Yes | W63: 1197 | X63: 89 | Y63: 22.38 | AB63: 5 | AC63: 5 | AD63: 268 | AF63: 6 | AG63: Yes | AH63: Yes | AI63: Yes | AJ63: Titan Grey | AK63: Like New | AL63: 9100 | AM63: 2026-12-09 | AN63: Karnataka | AO63: Bengaluru | AP63: Available | AQ63: 2026-09-08 | AR63: Dealer | AS63: Yes | AT63: Yes | AU63: No | AV63: SmartPlay Pro+ 9-inch Touchscreen, Cruise Control, LED Projector Headlamps, Auto AC | AW63: Well-maintained 2025 like new condition Maruti Suzuki Swift ZXi+ 1.2L DualJet (Manual) in Bengaluru. Powered by a 1197 cc petrol engine delivering 22.38 km/l. Complete service history available. | AX63: Daily Commuter | AY63: 6800 | AZ63: Synthetic Sample
A64: CAR-1063 | B64: Maruti Suzuki | C64: Maruti Suzuki Baleno | D64: Baleno | E64: Alpha 1.2L AGS | F64: 2020 | G64: 2020 | H64: Used | I64: Hatchback | J64: Petrol | K64: AMT | L64: 1 | M64: 460000 | N64: 840000 | O64: Yes | P64: 440000 | Q64: 115000 | R64: =IF(V64="No",0,MAX(0,M64-Q64)) -> 345000 | S64: 11.15 | T64: 60 | U64: =IF(OR(R64<=0,S64<0,T64<=0),"",IF(S64=0,R64/T64,-PMT(S64/1200,T64,R64))) -> 7527 | V64: Yes | W64: 1197 | X64: 89 | Y64: 22.94 | AB64: 5 | AC64: 5 | AD64: 318 | AE64: 4 Star (Bharat NCAP) | AF64: 6 | AG64: Yes | AH64: Yes | AI64: Yes | AJ64: Abyss Black | AK64: Excellent | AL64: 54300 | AM64: 2027-03-14 | AN64: Telangana | AO64: Hyderabad | AP64: Available | AQ64: 2026-10-11 | AR64: Dealer | AS64: Yes | AT64: No | AU64: No | AV64: Head-Up Display, 360 View Camera, 9-inch SmartPlay Pro+, UV Cut Glass | AW64: Well-maintained 2020 excellent condition Maruti Suzuki Baleno Alpha 1.2L AGS (AMT) in Hyderabad. Powered by a 1197 cc petrol engine delivering 22.94 km/l. Complete service history available. | AX64: Family | AY64: 8400 | AZ64: Synthetic Sample
A65: CAR-1064 | B65: Maruti Suzuki | C65: Maruti Suzuki Brezza | D65: Brezza | E65: ZXi+ 1.5L Smart Hybrid AT | F65: 2015 | G65: 2015 | H65: Used | I65: SUV | J65: Petrol | K65: Automatic | L65: 2 | M65: 310000 | N65: 1015000 | O65: No | P65: 310000 | Q65: 80000 | R65: =IF(V65="No",0,MAX(0,M65-Q65)) -> 0 | S65: 0 | T65: 0 | U65: =IF(OR(R65<=0,S65<0,T65<=0),"",IF(S65=0,R65/T65,-PMT(S65/1200,T65,R65))) | V65: No | W65: 1462 | X65: 102 | Y65: 19.8 | AB65: 5 | AC65: 5 | AD65: 328 | AE65: 4 Star (Global NCAP) | AF65: 6 | AG65: Yes | AH65: Yes | AI65: Yes | AJ65: Starry Night Blue | AK65: Fair | AL65: 105500 | AM65: 2026-12-19 | AN65: Maharashtra | AO65: Mumbai | AP65: Available | AQ65: 2026-09-14 | AR65: Individual | AS65: No | AT65: No | AU65: No | AV65: Electric Sunroof, Paddle Shifters, 360 Degree Camera, Wireless Charging | AW65: Well-maintained 2015 fair condition Maruti Suzuki Brezza ZXi+ 1.5L Smart Hybrid AT (Automatic) in Mumbai. Powered by a 1462 cc petrol engine delivering 19.8 km/l. Inspected for mechanical reliability. | AX65: Family | AY65: 11800 | AZ65: Synthetic Sample
A66: CAR-1065 | B66: Maruti Suzuki | C66: Maruti Suzuki Wagon R | D66: Wagon R | E66: VXi 1.0L S-CNG | F66: 2022 | G66: 2022 | H66: Used | I66: Hatchback | J66: CNG | K66: Manual | L66: 1 | M66: 415000 | N66: 620000 | O66: Yes | P66: 395000 | Q66: 105000 | R66: =IF(V66="No",0,MAX(0,M66-Q66)) -> 310000 | S66: 10.85 | T66: 48 | U66: =IF(OR(R66<=0,S66<0,T66<=0),"",IF(S66=0,R66/T66,-PMT(S66/1200,T66,R66))) -> 7990 | V66: Yes | W66: 998 | X66: 56 | Y66: 33.47 | AB66: 5 | AC66: 5 | AD66: 341 | AF66: 2 | AG66: Yes | AH66: No | AI66: Yes | AJ66: Pearl Arctic White | AK66: Excellent | AL66: 47200 | AM66: 2027-05-24 | AN66: Delhi | AO66: Delhi | AP66: Reserved | AQ66: 2026-10-17 | AR66: Dealer | AS66: Yes | AT66: Yes | AU66: No | AV66: Factory Fitted S-CNG Dual Interdependent ECUs, Keyless Entry, Power Windows | AW66: Well-maintained 2022 excellent condition Maruti Suzuki Wagon R VXi 1.0L S-CNG (Manual) in Delhi. Powered by a 998 cc cng engine delivering 33.47 km/l. Complete service history available. | AX66: First-Time Buyer | AY66: 6400 | AZ66: Synthetic Sample
A67: CAR-1066 | B67: Maruti Suzuki | C67: Maruti Suzuki Ertiga | D67: Ertiga | E67: ZXi 1.5L S-CNG | F67: 2017 | G67: 2018 | H67: Used | I67: MUV | J67: CNG | K67: Manual | L67: 2 | M67: 340000 | N67: 920000 | O67: Yes | P67: 325000 | Q67: 85000 | R67: =IF(V67="No",0,MAX(0,M67-Q67)) -> 255000 | S67: 11.6 | T67: 60 | U67: =IF(OR(R67<=0,S67<0,T67<=0),"",IF(S67=0,R67/T67,-PMT(S67/1200,T67,R67))) -> 5621 | V67: Yes | W67: 1462 | X67: 87 | Y67: 26.11 | AB67: 7 | AC67: 5 | AD67: 209 | AF67: 4 | AG67: Yes | AH67: Yes | AI67: Yes | AJ67: Titan Grey | AK67: Fair | AL67: 116100 | AM67: 2026-12-02 | AN67: Maharashtra | AO67: Pune | AP67: Sold | AQ67: 2026-09-20 | AR67: Dealer | AS67: Yes | AT67: No | AU67: No | AV67: 7-Seater Reclining Rows, Roof Mounted AC Vents, 7-inch SmartPlay Studio | AW67: Well-maintained 2017 fair condition Maruti Suzuki Ertiga ZXi 1.5L S-CNG (Manual) in Pune. Powered by a 1462 cc cng engine delivering 26.11 km/l. Complete service history available. | AX67: Family | AY67: 10600 | AZ67: Synthetic Sample
A68: CAR-1067 | B68: Maruti Suzuki | C68: Maruti Suzuki Grand Vitara | D68: Grand Vitara | E68: Alpha+ 1.5L Intelligent Electric Hybrid | F68: 2025 | G68: 2025 | H68: Used | I68: SUV | J68: Hybrid | K68: CVT | L68: 1 | M68: 1765000 | N68: 1950000 | O68: No | P68: 1765000 | Q68: 440000 | R68: =IF(V68="No",0,MAX(0,M68-Q68)) -> 1325000 | S68: 10.4 | T68: 36 | U68: =IF(OR(R68<=0,S68<0,T68<=0),"",IF(S68=0,R68/T68,-PMT(S68/1200,T68,R68))) -> 43003 | V68: Yes | W68: 1490 | X68: 114 | Y68: 27.97 | AB68: 5 | AC68: 5 | AD68: 265 | AE68: 5 Star (Bharat NCAP) | AF68: 6 | AG68: Yes | AH68: Yes | AI68: Yes | AJ68: Abyss Black | AK68: Like New | AL68: 11700 | AM68: 2027-07-07 | AN68: Tamil Nadu | AO68: Coimbatore | AP68: Available | AQ68: 2026-10-01 | AR68: Individual | AS68: Yes | AT68: Yes | AU68: No | AV68: Panoramic Sunroof, Ventilated Front Seats, Strong Hybrid e-CVT, TPMS | AW68: Well-maintained 2025 like new condition Maruti Suzuki Grand Vitara Alpha+ 1.5L Intelligent Electric Hybrid (CVT) in Coimbatore. Powered by a 1490 cc hybrid engine delivering 27.97 km/l. Complete service history available. | AX68: Family | AY68: 9600 | AZ68: Synthetic Sample
A69: CAR-1068 | B69: Maruti Suzuki | C69: Maruti Suzuki Dzire | D69: Dzire | E69: ZXi+ 1.2L AGS | F69: 2019 | G69: 2019 | H69: Used | I69: Sedan | J69: Petrol | K69: AMT | L69: 1 | M69: 415000 | N69: 835000 | O69: Yes | P69: 395000 | Q69: 105000 | R69: =IF(V69="No",0,MAX(0,M69-Q69)) -> 310000 | S69: 11.3 | T69: 48 | U69: =IF(OR(R69<=0,S69<0,T69<=0),"",IF(S69=0,R69/T69,-PMT(S69/1200,T69,R69))) -> 8057 | V69: Yes | W69: 1197 | X69: 80 | Y69: 25.71 | AB69: 5 | AC69: 4 | AD69: 382 | AE69: 5 Star (Global NCAP) | AF69: 6 | AG69: Yes | AH69: Yes | AI69: Yes | AJ69: Starry Night Blue | AK69: Good | AL69: 69600 | AM69: 2026-12-12 | AN69: Kerala | AO69: Kochi | AP69: Available | AQ69: 2026-09-04 | AR69: Dealer | AS69: Yes | AT69: No | AU69: No | AV69: Electric Sunroof, 360 HD View Camera, Wireless Android Auto & CarPlay | AW69: Well-maintained 2019 good condition Maruti Suzuki Dzire ZXi+ 1.2L AGS (AMT) in Kochi. Powered by a 1197 cc petrol engine delivering 25.71 km/l. Complete service history available. | AX69: Family | AY69: 8400 | AZ69: Synthetic Sample
A70: CAR-1069 | B70: Hyundai | C70: Hyundai Creta | D70: Creta | E70: SX (O) 1.5L Turbo GDi DCT | F70: 2026 | G70: 2026 | H70: New | I70: SUV | J70: Petrol | K70: DCT | L70: 0 | M70: 2015000 | N70: 2015000 | O70: Yes | P70: 1935000 | Q70: 405000 | R70: =IF(V70="No",0,MAX(0,M70-Q70)) -> 1610000 | S70: 8.95 | T70: 84 | U70: =IF(OR(R70<=0,S70<0,T70<=0),"",IF(S70=0,R70/T70,-PMT(S70/1200,T70,R70))) -> 25863 | V70: Yes | W70: 1482 | X70: 158 | Y70: 18.4 | AB70: 5 | AC70: 5 | AD70: 433 | AF70: 6 | AG70: Yes | AH70: Yes | AI70: Yes | AJ70: Pearl Arctic White | AK70: New | AL70: 38 | AM70: 2029-09-17 | AN70: Gujarat | AO70: Ahmedabad | AP70: Available | AQ70: 2026-10-07 | AR70: Dealer | AS70: Yes | AT70: Yes | AU70: No | AV70: Level 2 ADAS, Bose 8-Speaker Audio, Panoramic Sunroof, Dual 10.25-inch Displays | AW70: Brand-new 2026 showroom condition Hyundai Creta SX (O) 1.5L Turbo GDi DCT (DCT) in Ahmedabad. Powered by a 1482 cc petrol engine delivering 18.4 km/l. Complete service history available. | AX70: Family | AY70: 9800 | AZ70: Synthetic Sample
A71: CAR-1070 | B71: Hyundai | C71: Hyundai Creta | D71: Creta | E71: SX Tech 1.5L CRDi AT | F71: 2021 | G71: 2021 | H71: Used | I71: SUV | J71: Diesel | K71: Automatic | L71: 2 | M71: 1015000 | N71: 1670000 | O71: No | P71: 1015000 | Q71: 255000 | R71: =IF(V71="No",0,MAX(0,M71-Q71)) -> 760000 | S71: 11 | T71: 36 | U71: =IF(OR(R71<=0,S71<0,T71<=0),"",IF(S71=0,R71/T71,-PMT(S71/1200,T71,R71))) -> 24881 | V71: Yes | W71: 1493 | X71: 114 | Y71: 19.1 | AB71: 5 | AC71: 5 | AD71: 433 | AF71: 6 | AG71: Yes | AH71: Yes | AI71: Yes | AJ71: Titan Grey | AK71: Excellent | AL71: 57000 | AM71: 2026-12-22 | AN71: West Bengal | AO71: Kolkata | AP71: Available | AQ71: 2026-09-10 | AR71: Individual | AS71: Yes | AT71: No | AU71: No | AV71: Panoramic Sunroof, Voice Enabled Smart Controls, Bose Sound, Bluelink Connected Car | AW71: Well-maintained 2021 excellent condition Hyundai Creta SX Tech 1.5L CRDi AT (Automatic) in Kolkata. Powered by a 1493 cc diesel engine delivering 19.1 km/l. Complete service history available. | AX71: Family | AY71: 12600 | AZ71: Synthetic Sample
A72: CAR-1071 | B72: Hyundai | C72: Hyundai i20 | D72: i20 | E72: Asta (O) 1.2L Kappa IVT | F72: 2016 | G72: 2017 | H72: Used | I72: Hatchback | J72: Petrol | K72: CVT | L72: 2 | M72: 310000 | N72: 840000 | O72: Yes | P72: 295000 | Q72: 80000 | R72: =IF(V72="No",0,MAX(0,M72-Q72)) -> 230000 | S72: 11.75 | T72: 48 | U72: =IF(OR(R72<=0,S72<0,T72<=0),"",IF(S72=0,R72/T72,-PMT(S72/1200,T72,R72))) -> 6029 | V72: Yes | W72: 1197 | X72: 87 | Y72: 19.65 | AB72: 5 | AC72: 5 | AD72: 311 | AE72: 3 Star (Global NCAP) | AF72: 6 | AG72: Yes | AH72: Yes | AI72: Yes | AJ72: Abyss Black | AK72: Good | AL72: 76600 | AM72: 2027-11-27 | AN72: Tamil Nadu | AO72: Chennai | AP72: Reserved | AQ72: 2026-10-13 | AR72: Dealer | AS72: No | AT72: No | AU72: No | AV72: Electric Sunroof, Bose 7-Speaker System, 10.25-inch HD Infotainment, Ambient Lighting | AW72: Well-maintained 2016 good condition Hyundai i20 Asta (O) 1.2L Kappa IVT (CVT) in Chennai. Powered by a 1197 cc petrol engine delivering 19.65 km/l. Inspected for mechanical reliability. | AX72: Daily Commuter | AY72: 10400 | AZ72: Synthetic Sample
A73: CAR-1072 | B73: Hyundai | C73: Hyundai Verna | D73: Verna | E73: SX (O) 1.5L Turbo GDi DCT | F73: 2023 | G73: 2023 | H73: Used | I73: Sedan | J73: Petrol | K73: DCT | L73: 1 | M73: 1195000 | N73: 1610000 | O73: Yes | P73: 1145000 | Q73: 300000 | R73: =IF(V73="No",0,MAX(0,M73-Q73)) -> 895000 | S73: 10.7 | T73: 60 | U73: =IF(OR(R73<=0,S73<0,T73<=0),"",IF(S73=0,R73/T73,-PMT(S73/1200,T73,R73))) -> 19326 | V73: Yes | W73: 1482 | X73: 158 | Y73: 20.6 | AB73: 5 | AC73: 4 | AD73: 528 | AE73: 5 Star (Global NCAP) | AF73: 6 | AG73: Yes | AH73: Yes | AI73: Yes | AJ73: Starry Night Blue | AK73: Excellent | AL73: 28500 | AM73: 2026-12-05 | AN73: Karnataka | AO73: Bengaluru | AP73: Sold | AQ73: 2026-09-16 | AR73: Dealer | AS73: Yes | AT73: Yes | AU73: No | AV73: Hyundai SmartSense Level 2 ADAS, Heated & Ventilated Front Seats, Horizon LED Lamp | AW73: Well-maintained 2023 excellent condition Hyundai Verna SX (O) 1.5L Turbo GDi DCT (DCT) in Bengaluru. Powered by a 1482 cc petrol engine delivering 20.6 km/l. Complete service history available. | AX73: Enthusiast | AY73: 10200 | AZ73: Synthetic Sample
A74: CAR-1073 | B74: Hyundai | C74: Hyundai Venue | D74: Venue | E74: SX (O) 1.0L Turbo DCT | F74: 2018 | G74: 2018 | H74: Used | I74: SUV | J74: Petrol | K74: DCT | L74: 3 | M74: 485000 | N74: 1080000 | O74: No | P74: 485000 | Q74: 120000 | R74: =IF(V74="No",0,MAX(0,M74-Q74)) -> 365000 | S74: 11.45 | T74: 36 | U74: =IF(OR(R74<=0,S74<0,T74<=0),"",IF(S74=0,R74/T74,-PMT(S74/1200,T74,R74))) -> 12028 | V74: Yes | W74: 998 | X74: 118 | Y74: 18.31 | AB74: 5 | AC74: 5 | AD74: 350 | AF74: 6 | AG74: Yes | AH74: Yes | AI74: Yes | AJ74: Pearl Arctic White | AK74: Good | AL74: 68100 | AM74: 2027-01-10 | AN74: Telangana | AO74: Hyderabad | AP74: Available | AQ74: 2026-10-19 | AR74: Individual | AS74: Yes | AT74: No | AU74: No | AV74: Smart Electric Sunroof, 4-Way Power Driver Seat, Air Purifier, Dashcam | AW74: Well-maintained 2018 good condition Hyundai Venue SX (O) 1.0L Turbo DCT (DCT) in Hyderabad. Powered by a 998 cc petrol engine delivering 18.31 km/l. Complete service history available. | AX74: Daily Commuter | AY74: 10600 | AZ74: Synthetic Sample
A75: CAR-1074 | B75: Hyundai | C75: Hyundai Ioniq 5 | D75: Ioniq 5 | E75: RWD 72.6 kWh Long Range | F75: 2024 | G75: 2024 | H75: Used | I75: SUV | J75: Electric | K75: Automatic | L75: 1 | M75: 3585000 | N75: 4375000 | O75: Yes | P75: 3405000 | Q75: 895000 | R75: =IF(V75="No",0,MAX(0,M75-Q75)) -> 2690000 | S75: 10.55 | T75: 48 | U75: =IF(OR(R75<=0,S75<0,T75<=0),"",IF(S75=0,R75/T75,-PMT(S75/1200,T75,R75))) -> 68938 | V75: Yes | X75: 215 | Z75: 631 | AA75: 72.6 | AB75: 5 | AC75: 5 | AD75: 527 | AE75: 5 Star (Euro NCAP) | AF75: 6 | AG75: Yes | AH75: Yes | AI75: Yes | AJ75: Titan Grey | AK75: Like New | AL75: 23800 | AM75: 2026-12-15 | AN75: Maharashtra | AO75: Mumbai | AP75: Available | AQ75: 2026-09-22 | AR75: Dealer | AS75: Yes | AT75: Yes | AU75: No | AV75: 800V Ultra-Fast Charging, Vehicle-to-Load (V2L), Parametric Pixel LED, Level 2 ADAS | AW75: Well-maintained 2024 like new condition Hyundai Ioniq 5 RWD 72.6 kWh Long Range (Automatic) in Mumbai. Powered by a 72.6 kWh battery delivering 631 km certified range. Complete service history available. | AX75: Enthusiast | AY75: 6700 | AZ75: Synthetic Sample
A76: CAR-1075 | B76: Hyundai | C76: Hyundai Grand i10 Nios | D76: Grand i10 Nios | E76: Sportz 1.2L Hy-CNG Duo | F76: 2020 | G76: 2020 | H76: Used | I76: Hatchback | J76: CNG | K76: Manual | L76: 1 | M76: 350000 | N76: 705000 | O76: Yes | P76: 335000 | Q76: 90000 | R76: =IF(V76="No",0,MAX(0,M76-Q76)) -> 260000 | S76: 11.15 | T76: 60 | U76: =IF(OR(R76<=0,S76<0,T76<=0),"",IF(S76=0,R76/T76,-PMT(S76/1200,T76,R76))) -> 5672 | V76: Yes | W76: 1197 | X76: 68 | Y76: 27.3 | AB76: 5 | AC76: 5 | AD76: 240 | AF76: 6 | AG76: Yes | AH76: Yes | AI76: Yes | AJ76: Abyss Black | AK76: Good | AL76: 88900 | AM76: 2027-03-20 | AN76: Delhi | AO76: Delhi | AP76: Available | AQ76: 2026-10-03 | AR76: Dealer | AS76: Yes | AT76: No | AU76: No | AV76: Dual Cylinder CNG with Usable Boot, 8-inch Touchscreen, Rear AC Vents | AW76: Well-maintained 2020 good condition Hyundai Grand i10 Nios Sportz 1.2L Hy-CNG Duo (Manual) in Delhi. Powered by a 1197 cc cng engine delivering 27.3 km/l. Complete service history available. | AX76: First-Time Buyer | AY76: 7700 | AZ76: Synthetic Sample
A77: CAR-1076 | B77: Tata | C77: Tata Nexon | D77: Nexon | E77: Fearless+ S 1.2L Turbo DCA | F77: 2015 | G77: 2016 | H77: Used | I77: SUV | J77: Petrol | K77: DCT | L77: 2 | M77: 325000 | N77: 1075000 | O77: No | P77: 325000 | Q77: 80000 | R77: =IF(V77="No",0,MAX(0,M77-Q77)) -> 0 | S77: 0 | T77: 0 | U77: =IF(OR(R77<=0,S77<0,T77<=0),"",IF(S77=0,R77/T77,-PMT(S77/1200,T77,R77))) | V77: No | W77: 1199 | X77: 118 | Y77: 17.01 | AB77: 5 | AC77: 5 | AD77: 382 | AE77: 5 Star (Global & Bharat NCAP) | AF77: 6 | AG77: Yes | AH77: Yes | AI77: Yes | AJ77: Starry Night Blue | AK77: Fair | AL77: 120500 | AM77: 2026-12-25 | AN77: Maharashtra | AO77: Pune | AP77: Available | AQ77: 2026-09-06 | AR77: Individual | AS77: Yes | AT77: No | AU77: Unknown | AV77: 10.25-inch Harman Floating Infotainment, 360 Surround View, Ventilated Seats, JBL Audio | AW77: Well-maintained 2015 fair condition Tata Nexon Fearless+ S 1.2L Turbo DCA (DCT) in Pune. Powered by a 1199 cc petrol engine delivering 17.01 km/l. Complete service history available. | AX77: Family | AY77: 12200 | AZ77: Synthetic Sample
A78: CAR-1077 | B78: Tata | C78: Tata Nexon.ev | D78: Nexon.ev | E78: Empowered+ 45 kWh Long Range | F78: 2025 | G78: 2025 | H78: Used | I78: SUV | J78: Electric | K78: Automatic | L78: 1 | M78: 1500000 | N78: 1655000 | O78: Yes | P78: 1425000 | Q78: 375000 | R78: =IF(V78="No",0,MAX(0,M78-Q78)) -> 1125000 | S78: 10.4 | T78: 48 | U78: =IF(OR(R78<=0,S78<0,T78<=0),"",IF(S78=0,R78/T78,-PMT(S78/1200,T78,R78))) -> 28750 | V78: Yes | X78: 142 | Z78: 489 | AA78: 45 | AB78: 5 | AC78: 5 | AD78: 350 | AE78: 5 Star (Bharat NCAP) | AF78: 6 | AG78: Yes | AH78: Yes | AI78: Yes | AJ78: Pearl Arctic White | AK78: Like New | AL78: 10400 | AM78: 2027-05-03 | AN78: Tamil Nadu | AO78: Coimbatore | AP78: Reserved | AQ78: 2026-10-09 | AR78: Dealer | AS78: Yes | AT78: Yes | AU78: No | AV78: Panoramic Sunroof, V2V & V2L Charging, 12.3-inch Cinematic Screen, Arcade.ev App Suite | AW78: Well-maintained 2025 like new condition Tata Nexon.ev Empowered+ 45 kWh Long Range (Automatic) in Coimbatore. Powered by a 45 kWh battery delivering 489 km certified range. Complete service history available. | AX78: Daily Commuter | AY78: 5000 | AZ78: Synthetic Sample
A79: CAR-1078 | B79: Tata | C79: Tata Punch | D79: Punch | E79: Accomplished+ S iCNG | F79: 2017 | G79: 2017 | H79: Used | I79: SUV | J79: CNG | K79: Manual | L79: 2 | M79: 285000 | N79: 765000 | O79: Yes | P79: 275000 | Q79: 70000 | R79: =IF(V79="No",0,MAX(0,M79-Q79)) -> 215000 | S79: 11.6 | T79: 60 | U79: =IF(OR(R79<=0,S79<0,T79<=0),"",IF(S79=0,R79/T79,-PMT(S79/1200,T79,R79))) -> 4739 | V79: Yes | W79: 1199 | X79: 72 | Y79: 26.99 | AB79: 5 | AC79: 5 | AD79: 210 | AE79: 5 Star (Global NCAP) | AF79: 2 | AG79: Yes | AH79: Yes | AI79: Yes | AJ79: Titan Grey | AK79: Fair | AL79: 114100 | AM79: 2026-12-08 | AN79: Kerala | AO79: Kochi | AP79: Sold | AQ79: 2026-09-12 | AR79: Dealer | AS79: No | AT79: No | AU79: No | AV79: Twin-Cylinder iCNG Technology, Voice Assisted Electric Sunroof, 7-inch Harman Screen | AW79: Well-maintained 2017 fair condition Tata Punch Accomplished+ S iCNG (Manual) in Kochi. Powered by a 1199 cc cng engine delivering 26.99 km/l. Inspected for mechanical reliability. | AX79: First-Time Buyer | AY79: 8700 | AZ79: Synthetic Sample
A80: CAR-1079 | B80: Tata | C80: Tata Punch.ev | D80: Punch.ev | E80: Empowered+ S 35 kWh Long Range | F80: 2025 | G80: 2025 | H80: Used | I80: SUV | J80: Electric | K80: Automatic | L80: 1 | M80: 1280000 | N80: 1415000 | O80: No | P80: 1280000 | Q80: 320000 | R80: =IF(V80="No",0,MAX(0,M80-Q80)) -> 960000 | S80: 10.4 | T80: 36 | U80: =IF(OR(R80<=0,S80<0,T80<=0),"",IF(S80=0,R80/T80,-PMT(S80/1200,T80,R80))) -> 31157 | V80: Yes | X80: 120 | Z80: 421 | AA80: 35 | AB80: 5 | AC80: 5 | AD80: 366 | AE80: 5 Star (Bharat NCAP) | AF80: 6 | AG80: Yes | AH80: Yes | AI80: Yes | AJ80: Abyss Black | AK80: Like New | AL80: 9800 | AM80: 2027-07-13 | AN80: Gujarat | AO80: Ahmedabad | AP80: Available | AQ80: 2026-10-15 | AR80: Individual | AS80: Yes | AT80: Yes | AU80: No | AV80: acti.ev Pure EV Architecture, Frunk Storage, 360 Camera, Electronic Parking Brake | AW80: Well-maintained 2025 like new condition Tata Punch.ev Empowered+ S 35 kWh Long Range (Automatic) in Ahmedabad. Powered by a 35 kWh battery delivering 421 km certified range. Complete service history available. | AX80: Daily Commuter | AY80: 4700 | AZ80: Synthetic Sample
A81: CAR-1080 | B81: Tata | C81: Tata Harrier | D81: Harrier | E81: Fearless+ Dark 2.0L Kryotec AT | F81: 2019 | G81: 2019 | H81: Used | I81: SUV | J81: Diesel | K81: Automatic | L81: 1 | M81: 980000 | N81: 2165000 | O81: Yes | P81: 930000 | Q81: 245000 | R81: =IF(V81="No",0,MAX(0,M81-Q81)) -> 735000 | S81: 11.3 | T81: 48 | U81: =IF(OR(R81<=0,S81<0,T81<=0),"",IF(S81=0,R81/T81,-PMT(S81/1200,T81,R81))) -> 19104 | V81: Yes | W81: 1956 | X81: 168 | Y81: 16.8 | AB81: 5 | AC81: 5 | AD81: 445 | AE81: 5 Star (Global & Bharat NCAP) | AF81: 7 | AG81: Yes | AH81: Yes | AI81: Yes | AJ81: Starry Night Blue | AK81: Good | AL81: 94400 | AM81: 2026-12-18 | AN81: West Bengal | AO81: Kolkata | AP81: Available | AQ81: 2026-09-18 | AR81: Dealer | AS81: Yes | AT81: No | AU81: No | AV81: ADAS Level 2, Gesture Controlled Powered Tailgate, Dual-Zone Climate Control, Panoramic Sunroof | AW81: Well-maintained 2019 good condition Tata Harrier Fearless+ Dark 2.0L Kryotec AT (Automatic) in Kolkata. Powered by a 1956 cc diesel engine delivering 16.8 km/l. Complete service history available. | AX81: Family | AY81: 16000 | AZ81: Synthetic Sample
A82: CAR-1081 | B82: Tata | C82: Tata Safari | D82: Safari | E82: Accomplished+ 2.0L Kryotec AT 6S | F82: 2026 | G82: 2026 | H82: New | I82: SUV | J82: Diesel | K82: Automatic | L82: 0 | M82: 2734000 | N82: 2735000 | O82: Yes | P82: 2625000 | Q82: 545000 | R82: =IF(V82="No",0,MAX(0,M82-Q82)) -> 2189000 | S82: 8.95 | T82: 84 | U82: =IF(OR(R82<=0,S82<0,T82<=0),"",IF(S82=0,R82/T82,-PMT(S82/1200,T82,R82))) -> 35163 | V82: Yes | W82: 1956 | X82: 168 | Y82: 16.3 | AB82: 6 | AC82: 5 | AD82: 420 | AE82: 5 Star (Global & Bharat NCAP) | AF82: 7 | AG82: Yes | AH82: Yes | AI82: Yes | AJ82: Pearl Arctic White | AK82: New | AL82: 50 | AM82: 2029-09-23 | AN82: Tamil Nadu | AO82: Chennai | AP82: Available | AQ82: 2026-10-21 | AR82: Dealer | AS82: Yes | AT82: Yes | AU82: No | AV82: 2nd Row Ventilated Captain Seats, Boss Mode, 10-Speaker JBL Dolby Atmos, Panoramic Sunroof | AW82: Brand-new 2026 showroom condition Tata Safari Accomplished+ 2.0L Kryotec AT 6S (Automatic) in Chennai. Powered by a 1956 cc diesel engine delivering 16.3 km/l. Complete service history available. | AX82: Family | AY82: 13200 | AZ82: Synthetic Sample
A83: CAR-1082 | B83: Tata | C83: Tata Curvv.ev | D83: Curvv.ev | E83: Empowered+ A 55 kWh | F83: 2024 | G83: 2024 | H83: Used | I83: Coupe | J83: Electric | K83: Automatic | L83: 1 | M83: 1710000 | N83: 2090000 | O83: No | P83: 1710000 | Q83: 430000 | R83: =IF(V83="No",0,MAX(0,M83-Q83)) -> 1280000 | S83: 10.55 | T83: 36 | U83: =IF(OR(R83<=0,S83<0,T83<=0),"",IF(S83=0,R83/T83,-PMT(S83/1200,T83,R83))) -> 41633 | V83: Yes | X83: 165 | Z83: 585 | AA83: 55 | AB83: 5 | AC83: 5 | AD83: 500 | AE83: 5 Star (Bharat NCAP) | AF83: 6 | AG83: Yes | AH83: Yes | AI83: Yes | AJ83: Titan Grey | AK83: Like New | AL83: 23600 | AM83: 2026-12-01 | AN83: Karnataka | AO83: Bengaluru | AP83: Available | AQ83: 2026-09-02 | AR83: Individual | AS83: Yes | AT83: Yes | AU83: No | AV83: SUV Coupe Design, Level 2 ADAS (20 Features), Acoustic Vehicle Alert System, Powered Tailgate | AW83: Well-maintained 2024 like new condition Tata Curvv.ev Empowered+ A 55 kWh (Automatic) in Bengaluru. Powered by a 55 kWh battery delivering 585 km certified range. Complete service history available. | AX83: Enthusiast | AY83: 5600 | AZ83: Synthetic Sample
A84: CAR-1083 | B84: Mahindra | C84: Mahindra XUV700 | D84: XUV700 | E84: AX7 Luxury Pack 2.2L mHawk AT AWD | F84: 2016 | G84: 2016 | H84: Used | I84: SUV | J84: Diesel | K84: Automatic | L84: 2 | M84: 640000 | N84: 1910000 | O84: Yes | P84: 610000 | Q84: 160000 | R84: =IF(V84="No",0,MAX(0,M84-Q84)) -> 480000 | S84: 11.75 | T84: 48 | U84: =IF(OR(R84<=0,S84<0,T84<=0),"",IF(S84=0,R84/T84,-PMT(S84/1200,T84,R84))) -> 12581 | V84: Yes | W84: 2198 | X84: 182 | Y84: 15.5 | AB84: 7 | AC84: 5 | AD84: 240 | AE84: 5 Star (Global NCAP) | AF84: 7 | AG84: Yes | AH84: Yes | AI84: Yes | AJ84: Abyss Black | AK84: Fair | AL84: 124500 | AM84: 2027-11-06 | AN84: Telangana | AO84: Hyderabad | AP84: Reserved | AQ84: 2026-10-05 | AR84: Dealer | AS84: Yes | AT84: No | AU84: No | AV84: Skyroof Panoramic Sunroof, Adrenox Dual 10.25-inch Screens, Sony 12-Speaker 3D Audio, ADAS | AW84: Well-maintained 2016 fair condition Mahindra XUV700 AX7 Luxury Pack 2.2L mHawk AT AWD (Automatic) in Hyderabad. Powered by a 2198 cc diesel engine delivering 15.5 km/l. Complete service history available. | AX84: Family | AY84: 17900 | AZ84: Synthetic Sample
A85: CAR-1084 | B85: Mahindra | C85: Mahindra Scorpio-N | D85: Scorpio-N | E85: Z8L 2.2L mHawk 4XPLOR AT | F85: 2023 | G85: 2023 | H85: Used | I85: SUV | J85: Diesel | K85: Automatic | L85: 1 | M85: 1685000 | N85: 2270000 | O85: Yes | P85: 1620000 | Q85: 420000 | R85: =IF(V85="No",0,MAX(0,M85-Q85)) -> 1265000 | S85: 10.7 | T85: 60 | U85: =IF(OR(R85<=0,S85<0,T85<=0),"",IF(S85=0,R85/T85,-PMT(S85/1200,T85,R85))) -> 27315 | V85: Yes | W85: 2198 | X85: 172 | Y85: 15.4 | AB85: 7 | AC85: 5 | AD85: 460 | AE85: 5 Star (Global NCAP) | AF85: 6 | AG85: Yes | AH85: Yes | AI85: Yes | AJ85: Starry Night Blue | AK85: Excellent | AL85: 35800 | AM85: 2026-12-11 | AN85: Maharashtra | AO85: Mumbai | AP85: Sold | AQ85: 2026-09-08 | AR85: Dealer | AS85: Yes | AT85: Yes | AU85: No | AV85: 4XPLOR Terrain Management, Body-on-Frame 4WD, Sony 3D Audio, Ventilated Seats | AW85: Well-maintained 2023 excellent condition Mahindra Scorpio-N Z8L 2.2L mHawk 4XPLOR AT (Automatic) in Mumbai. Powered by a 2198 cc diesel engine delivering 15.4 km/l. Complete service history available. | AX85: Enthusiast | AY85: 13700 | AZ85: Synthetic Sample
A86: CAR-1085 | B86: Mahindra | C86: Mahindra Thar ROXX | D86: Thar ROXX | E86: AX7L 2.2L mHawk 4WD AT | F86: 2023 | G86: 2023 | H86: Used | I86: SUV | J86: Diesel | K86: Automatic | L86: 1 | M86: 1540000 | N86: 2080000 | O86: No | P86: 1540000 | Q86: 385000 | R86: =IF(V86="No",0,MAX(0,M86-Q86)) -> 1155000 | S86: 10.7 | T86: 36 | U86: =IF(OR(R86<=0,S86<0,T86<=0),"",IF(S86=0,R86/T86,-PMT(S86/1200,T86,R86))) -> 37649 | V86: Yes | W86: 2184 | X86: 172 | Y86: 15.2 | AB86: 5 | AC86: 5 | AD86: 447 | AE86: 5 Star (Bharat NCAP) | AF86: 6 | AG86: Yes | AH86: Yes | AI86: Yes | AJ86: Pearl Arctic White | AK86: Excellent | AL86: 44300 | AM86: 2027-01-16 | AN86: Delhi | AO86: Delhi | AP86: Available | AQ86: 2026-10-11 | AR86: Individual | AS86: No | AT86: Yes | AU86: No | AV86: 5-Door Off-Roader, CrawlSmart, IntelliTurn, Panoramic Skyroof, Harman Kardon 9-Speaker Audio | AW86: Well-maintained 2023 excellent condition Mahindra Thar ROXX AX7L 2.2L mHawk 4WD AT (Automatic) in Delhi. Powered by a 2184 cc diesel engine delivering 15.2 km/l. Inspected for mechanical reliability. | AX86: Enthusiast | AY86: 13200 | AZ86: Synthetic Sample
A87: CAR-1086 | B87: Mahindra | C87: Mahindra XUV 3XO | D87: XUV 3XO | E87: AX7L 1.2L TGDi AT | F87: 2024 | G87: 2025 | H87: Used | I87: SUV | J87: Petrol | K87: Automatic | L87: 1 | M87: 1205000 | N87: 1470000 | O87: Yes | P87: 1145000 | Q87: 300000 | R87: =IF(V87="No",0,MAX(0,M87-Q87)) -> 905000 | S87: 10.55 | T87: 48 | U87: =IF(OR(R87<=0,S87<0,T87<=0),"",IF(S87=0,R87/T87,-PMT(S87/1200,T87,R87))) -> 23193 | V87: Yes | W87: 1197 | X87: 129 | Y87: 18.2 | AB87: 5 | AC87: 5 | AD87: 364 | AE87: 5 Star (Bharat NCAP) | AF87: 6 | AG87: Yes | AH87: Yes | AI87: Yes | AJ87: Titan Grey | AK87: Like New | AL87: 17300 | AM87: 2026-12-21 | AN87: Maharashtra | AO87: Pune | AP87: Available | AQ87: 2026-09-14 | AR87: Dealer | AS87: Yes | AT87: Yes | AU87: No | AV87: Segment-First Skyroof, Level 2 ADAS, Harman Kardon Audio with Amplifier, Dual-Zone AC | AW87: Well-maintained 2024 like new condition Mahindra XUV 3XO AX7L 1.2L TGDi AT (Automatic) in Pune. Powered by a 1197 cc petrol engine delivering 18.2 km/l. Complete service history available. | AX87: Family | AY87: 9100 | AZ87: Synthetic Sample
A88: CAR-1087 | B88: Mahindra | C88: Mahindra BE 6 | D88: BE 6 | E88: Pack Three 79 kWh | F88: 2025 | G88: 2025 | H88: Used | I88: Coupe | J88: Electric | K88: Automatic | L88: 1 | M88: 2375000 | N88: 2625000 | O88: Yes | P88: 2280000 | Q88: 595000 | R88: =IF(V88="No",0,MAX(0,M88-Q88)) -> 1780000 | S88: 10.4 | T88: 60 | U88: =IF(OR(R88<=0,S88<0,T88<=0),"",IF(S88=0,R88/T88,-PMT(S88/1200,T88,R88))) -> 38171 | V88: Yes | X88: 282 | Z88: 682 | AA88: 79 | AB88: 5 | AC88: 5 | AD88: 455 | AE88: 5 Star (Bharat NCAP) | AF88: 7 | AG88: Yes | AH88: Yes | AI88: Yes | AJ88: Abyss Black | AK88: Like New | AL88: 11400 | AM88: 2027-03-26 | AN88: Tamil Nadu | AO88: Coimbatore | AP88: Available | AQ88: 2026-10-17 | AR88: Dealer | AS88: Yes | AT88: Yes | AU88: No | AV88: INGLO Born Electric Platform, Infinity Roof, 16-Speaker Harman Kardon Dolby Atmos, AR HUD | AW88: Well-maintained 2025 like new condition Mahindra BE 6 Pack Three 79 kWh (Automatic) in Coimbatore. Powered by a 79 kWh battery delivering 682 km certified range. Complete service history available. | AX88: Enthusiast | AY88: 6000 | AZ88: Synthetic Sample
A89: CAR-1088 | B89: Honda | C89: Honda City | D89: City | E89: ZX 1.5L i-VTEC CVT | F89: 2015 | G89: 2015 | H89: Used | I89: Sedan | J89: Petrol | K89: CVT | L89: 2 | M89: 360000 | N89: 1185000 | O89: No | P89: 360000 | Q89: 90000 | R89: =IF(V89="No",0,MAX(0,M89-Q89)) -> 0 | S89: 0 | T89: 0 | U89: =IF(OR(R89<=0,S89<0,T89<=0),"",IF(S89=0,R89/T89,-PMT(S89/1200,T89,R89))) | V89: No | W89: 1498 | X89: 119 | Y89: 18.4 | AB89: 5 | AC89: 4 | AD89: 506 | AE89: 5 Star (ASEAN NCAP) | AF89: 6 | AG89: Yes | AH89: Yes | AI89: Yes | AJ89: Starry Night Blue | AK89: Fair | AL89: 98200 | AM89: 2026-12-04 | AN89: Kerala | AO89: Kochi | AP89: Available | AQ89: 2026-09-20 | AR89: Individual | AS89: Yes | AT89: No | AU89: No | AV89: Honda Sensing ADAS, LaneWatch Camera, Electric Sunroof, Walk Away Auto Lock | AW89: Well-maintained 2015 fair condition Honda City ZX 1.5L i-VTEC CVT (CVT) in Kochi. Powered by a 1498 cc petrol engine delivering 18.4 km/l. Complete service history available. | AX89: Family | AY89: 12200 | AZ89: Synthetic Sample
A90: CAR-1089 | B90: Honda | C90: Honda City e:HEV | D90: City e:HEV | E90: ZX 1.5L Atkinson e-CVT | F90: 2022 | G90: 2022 | H90: Used | I90: Sedan | J90: Hybrid | K90: CVT | L90: 1 | M90: 1240000 | N90: 1850000 | O90: Yes | P90: 1180000 | Q90: 310000 | R90: =IF(V90="No",0,MAX(0,M90-Q90)) -> 930000 | S90: 10.85 | T90: 48 | U90: =IF(OR(R90<=0,S90<0,T90<=0),"",IF(S90=0,R90/T90,-PMT(S90/1200,T90,R90))) -> 23969 | V90: Yes | W90: 1498 | X90: 124 | Y90: 27.13 | AB90: 5 | AC90: 4 | AD90: 410 | AE90: 5 Star (ASEAN NCAP) | AF90: 6 | AG90: Yes | AH90: Yes | AI90: Yes | AJ90: Pearl Arctic White | AK90: Excellent | AL90: 46300 | AM90: 2027-05-09 | AN90: Gujarat | AO90: Ahmedabad | AP90: Reserved | AQ90: 2026-10-01 | AR90: Dealer | AS90: Yes | AT90: Yes | AU90: No | AV90: Self-Charging Strong Two-Motor Hybrid, Honda Sensing ADAS, Electronic Parking Brake | AW90: Well-maintained 2022 excellent condition Honda City e:HEV ZX 1.5L Atkinson e-CVT (CVT) in Ahmedabad. Powered by a 1498 cc hybrid engine delivering 27.13 km/l. Complete service history available. | AX90: Business | AY90: 10600 | AZ90: Synthetic Sample
A91: CAR-1090 | B91: Honda | C91: Honda Elevate | D91: Elevate | E91: ZX 1.5L i-VTEC CVT | F91: 2024 | G91: 2024 | H91: Used | I91: SUV | J91: Petrol | K91: CVT | L91: 1 | M91: 1280000 | N91: 1560000 | O91: Yes | P91: 1230000 | Q91: 320000 | R91: =IF(V91="No",0,MAX(0,M91-Q91)) -> 960000 | S91: 10.55 | T91: 60 | U91: =IF(OR(R91<=0,S91<0,T91<=0),"",IF(S91=0,R91/T91,-PMT(S91/1200,T91,R91))) -> 20658 | V91: Yes | W91: 1498 | X91: 119 | Y91: 16.92 | AB91: 5 | AC91: 5 | AD91: 458 | AF91: 6 | AG91: Yes | AH91: Yes | AI91: Yes | AJ91: Titan Grey | AK91: Like New | AL91: 20000 | AM91: 2026-12-14 | AN91: West Bengal | AO91: Kolkata | AP91: Sold | AQ91: 2026-09-04 | AR91: Dealer | AS91: Yes | AT91: Yes | AU91: No | AV91: 220mm Ground Clearance, Honda Sensing ADAS, 10.25-inch IPS HD Touchscreen, Sunroof | AW91: Well-maintained 2024 like new condition Honda Elevate ZX 1.5L i-VTEC CVT (CVT) in Kolkata. Powered by a 1498 cc petrol engine delivering 16.92 km/l. Complete service history available. | AX91: Family | AY91: 9300 | AZ91: Synthetic Sample
A92: CAR-1091 | B92: Honda | C92: Honda Amaze | D92: Amaze | E92: ZX 1.2L i-VTEC CVT | F92: 2024 | G92: 2025 | H92: Used | I92: Sedan | J92: Petrol | K92: CVT | L92: 1 | M92: 850000 | N92: 1035000 | O92: No | P92: 850000 | Q92: 215000 | R92: =IF(V92="No",0,MAX(0,M92-Q92)) -> 635000 | S92: 10.55 | T92: 36 | U92: =IF(OR(R92<=0,S92<0,T92<=0),"",IF(S92=0,R92/T92,-PMT(S92/1200,T92,R92))) -> 20654 | V92: Yes | W92: 1199 | X92: 89 | Y92: 19.46 | AB92: 5 | AC92: 4 | AD92: 416 | AF92: 6 | AG92: Yes | AH92: Yes | AI92: Yes | AJ92: Abyss Black | AK92: Like New | AL92: 15500 | AM92: 2027-07-19 | AN92: Tamil Nadu | AO92: Chennai | AP92: Available | AQ92: 2026-10-07 | AR92: Individual | AS92: Yes | AT92: Yes | AU92: Unknown | AV92: Honda Sensing ADAS, LaneWatch Camera, Wireless Charger, Paddle Shifters | AW92: Well-maintained 2024 like new condition Honda Amaze ZX 1.2L i-VTEC CVT (CVT) in Chennai. Powered by a 1199 cc petrol engine delivering 19.46 km/l. Complete service history available. | AX92: First-Time Buyer | AY92: 7700 | AZ92: Synthetic Sample
A93: CAR-1092 | B93: Toyota | C93: Toyota Innova Hycross | D93: Innova Hycross | E93: ZX (O) 2.0L Strong Hybrid e-Drive | F93: 2026 | G93: 2026 | H93: New | I93: MUV | J93: Hybrid | K93: CVT | L93: 0 | M93: 3098000 | N93: 3100000 | O93: No | P93: 3098000 | Q93: 620000 | R93: =IF(V93="No",0,MAX(0,M93-Q93)) -> 2478000 | S93: 8.95 | T93: 72 | U93: =IF(OR(R93<=0,S93<0,T93<=0),"",IF(S93=0,R93/T93,-PMT(S93/1200,T93,R93))) -> 44606 | V93: Yes | W93: 1987 | X93: 184 | Y93: 23.24 | AB93: 7 | AC93: 5 | AD93: 300 | AE93: 5 Star (Bharat NCAP) | AF93: 6 | AG93: Yes | AH93: Yes | AI93: Yes | AJ93: Starry Night Blue | AK93: New | AL93: 16 | AM93: 2029-08-24 | AN93: Karnataka | AO93: Bengaluru | AP93: Available | AQ93: 2026-09-10 | AR93: Dealer | AS93: Yes | AT93: Yes | AU93: No | AV93: Powered Ottoman 2nd Row Seats, Toyota Safety Sense ADAS, Panoramic Sunroof, JBL Audio | AW93: Brand-new 2026 showroom condition Toyota Innova Hycross ZX (O) 2.0L Strong Hybrid e-Drive (CVT) in Bengaluru. Powered by a 1987 cc hybrid engine delivering 23.24 km/l. Complete service history available. | AX93: Family | AY93: 10200 | AZ93: Synthetic Sample
A94: CAR-1093 | B94: Toyota | C94: Toyota Fortuner | D94: Fortuner | E94: Legender 2.8L 4x4 AT | F94: 2026 | G94: 2026 | H94: New | I94: SUV | J94: Diesel | K94: Automatic | L94: 0 | M94: 4764000 | N94: 4765000 | O94: Yes | P94: 4575000 | Q94: 955000 | R94: =IF(V94="No",0,MAX(0,M94-Q94)) -> 3809000 | S94: 8.95 | T94: 84 | U94: =IF(OR(R94<=0,S94<0,T94<=0),"",IF(S94=0,R94/T94,-PMT(S94/1200,T94,R94))) -> 61187 | V94: Yes | W94: 2755 | X94: 201 | Y94: 14.2 | AB94: 7 | AC94: 5 | AD94: 296 | AE94: 5 Star (ASEAN NCAP) | AF94: 7 | AG94: Yes | AH94: Yes | AI94: Yes | AJ94: Pearl Arctic White | AK94: New | AL94: 17 | AM94: 2029-09-02 | AN94: Telangana | AO94: Hyderabad | AP94: Available | AQ94: 2026-10-13 | AR94: Dealer | AS94: Yes | AT94: Yes | AU94: No | AV94: Quad-LED Headlamps, Active Traction Control (A-TRC), Kick-Sensor Powered Tailgate, JBL 11-Speaker | AW94: Brand-new 2026 showroom condition Toyota Fortuner Legender 2.8L 4x4 AT (Automatic) in Hyderabad. Powered by a 2755 cc diesel engine delivering 14.2 km/l. Complete service history available. | AX94: Business | AY94: 14500 | AZ94: Synthetic Sample
A95: CAR-1094 | B95: Toyota | C95: Toyota Urban Cruiser Hyryder | D95: Urban Cruiser Hyryder | E95: V 1.5L e-Drive Hybrid | F95: 2024 | G95: 2024 | H95: Used | I95: SUV | J95: Hybrid | K95: CVT | L95: 1 | M95: 1575000 | N95: 1920000 | O95: No | P95: 1575000 | Q95: 395000 | R95: =IF(V95="No",0,MAX(0,M95-Q95)) -> 1180000 | S95: 10.55 | T95: 36 | U95: =IF(OR(R95<=0,S95<0,T95<=0),"",IF(S95=0,R95/T95,-PMT(S95/1200,T95,R95))) -> 38381 | V95: Yes | W95: 1490 | X95: 114 | Y95: 27.97 | AB95: 5 | AC95: 5 | AD95: 265 | AF95: 6 | AG95: Yes | AH95: Yes | AI95: Yes | AJ95: Titan Grey | AK95: Like New | AL95: 16500 | AM95: 2026-12-07 | AN95: Maharashtra | AO95: Mumbai | AP95: Available | AQ95: 2026-09-16 | AR95: Individual | AS95: Yes | AT95: Yes | AU95: No | AV95: Self-Charging Strong Hybrid, Panoramic Sunroof, Head-Up Display, Ventilated Leather Seats | AW95: Well-maintained 2024 like new condition Toyota Urban Cruiser Hyryder V 1.5L e-Drive Hybrid (CVT) in Mumbai. Powered by a 1490 cc hybrid engine delivering 27.97 km/l. Complete service history available. | AX95: Family | AY95: 9600 | AZ95: Synthetic Sample
A96: CAR-1095 | B96: Toyota | C96: Toyota Glanza | D96: Glanza | E96: V 1.2L DualJet AMT | F96: 2016 | G96: 2016 | H96: Used | I96: Hatchback | J96: Petrol | K96: AMT | L96: 2 | M96: 250000 | N96: 750000 | O96: Yes | P96: 240000 | Q96: 65000 | R96: =IF(V96="No",0,MAX(0,M96-Q96)) -> 185000 | S96: 11.75 | T96: 48 | U96: =IF(OR(R96<=0,S96<0,T96<=0),"",IF(S96=0,R96/T96,-PMT(S96/1200,T96,R96))) -> 4849 | V96: Yes | W96: 1197 | X96: 89 | Y96: 22.94 | AB96: 5 | AC96: 5 | AD96: 318 | AF96: 6 | AG96: Yes | AH96: Yes | AI96: Yes | AJ96: Abyss Black | AK96: Fair | AL96: 113300 | AM96: 2027-11-12 | AN96: Delhi | AO96: Delhi | AP96: Reserved | AQ96: 2026-10-19 | AR96: Dealer | AS96: Yes | AT96: No | AU96: No | AV96: 360 Degree Camera, HUD, 9-inch Smart Playcast, Toyota i-Connect | AW96: Well-maintained 2016 fair condition Toyota Glanza V 1.2L DualJet AMT (AMT) in Delhi. Powered by a 1197 cc petrol engine delivering 22.94 km/l. Complete service history available. | AX96: Daily Commuter | AY96: 9100 | AZ96: Synthetic Sample
A97: CAR-1096 | B97: Kia | C97: Kia Seltos | D97: Seltos | E97: GTX+ 1.5L Turbo GDi DCT | F97: 2023 | G97: 2024 | H97: Used | I97: SUV | J97: Petrol | K97: DCT | L97: 1 | M97: 1395000 | N97: 1880000 | O97: Yes | P97: 1340000 | Q97: 350000 | R97: =IF(V97="No",0,MAX(0,M97-Q97)) -> 1045000 | S97: 10.7 | T97: 60 | U97: =IF(OR(R97<=0,S97<0,T97<=0),"",IF(S97=0,R97/T97,-PMT(S97/1200,T97,R97))) -> 22565 | V97: Yes | W97: 1482 | X97: 158 | Y97: 17.9 | AB97: 5 | AC97: 5 | AD97: 433 | AF97: 6 | AG97: Yes | AH97: Yes | AI97: Yes | AJ97: Starry Night Blue | AK97: Like New | AL97: 23700 | AM97: 2026-12-17 | AN97: Maharashtra | AO97: Pune | AP97: Sold | AQ97: 2026-09-22 | AR97: Dealer | AS97: Yes | AT97: Yes | AU97: No | AV97: ADAS Level 2 (19 Autonomous Features), Dual Pane Panoramic Sunroof, Bose 8-Speaker Audio | AW97: Well-maintained 2023 like new condition Kia Seltos GTX+ 1.5L Turbo GDi DCT (DCT) in Pune. Powered by a 1482 cc petrol engine delivering 17.9 km/l. Complete service history available. | AX97: Family | AY97: 11100 | AZ97: Synthetic Sample
A98: CAR-1097 | B98: Kia | C98: Kia Sonet | D98: Sonet | E98: GTX+ 1.5L CRDi AT | F98: 2018 | G98: 2018 | H98: Used | I98: SUV | J98: Diesel | K98: Automatic | L98: 3 | M98: 510000 | N98: 1250000 | O98: No | P98: 510000 | Q98: 130000 | R98: =IF(V98="No",0,MAX(0,M98-Q98)) -> 380000 | S98: 11.45 | T98: 36 | U98: =IF(OR(R98<=0,S98<0,T98<=0),"",IF(S98=0,R98/T98,-PMT(S98/1200,T98,R98))) -> 12522 | V98: Yes | W98: 1493 | X98: 114 | Y98: 18.6 | AB98: 5 | AC98: 5 | AD98: 385 | AF98: 6 | AG98: Yes | AH98: Yes | AI98: Yes | AJ98: Pearl Arctic White | AK98: Fair | AL98: 107000 | AM98: 2027-01-22 | AN98: Tamil Nadu | AO98: Coimbatore | AP98: Available | AQ98: 2026-10-03 | AR98: Individual | AS98: Yes | AT98: No | AU98: No | AV98: Level 1 ADAS, 360 Surround View Monitor, Ventilated Front Seats, Bose 7-Speaker System | AW98: Well-maintained 2018 fair condition Kia Sonet GTX+ 1.5L CRDi AT (Automatic) in Coimbatore. Powered by a 1493 cc diesel engine delivering 18.6 km/l. Complete service history available. | AX98: Daily Commuter | AY98: 11500 | AZ98: Synthetic Sample
A99: CAR-1098 | B99: Kia | C99: Kia Carens | D99: Carens | E99: Luxury Plus 1.5L Turbo DCT 7S | F99: 2025 | G99: 2025 | H99: Used | I99: MUV | J99: Petrol | K99: DCT | L99: 1 | M99: 1715000 | N99: 1895000 | O99: Yes | P99: 1630000 | Q99: 430000 | R99: =IF(V99="No",0,MAX(0,M99-Q99)) -> 1285000 | S99: 10.4 | T99: 48 | U99: =IF(OR(R99<=0,S99<0,T99<=0),"",IF(S99=0,R99/T99,-PMT(S99/1200,T99,R99))) -> 32838 | V99: Yes | W99: 1482 | X99: 158 | Y99: 16.8 | AB99: 7 | AC99: 5 | AD99: 216 | AE99: 3 Star (Global NCAP) | AF99: 6 | AG99: Yes | AH99: Yes | AI99: Yes | AJ99: Titan Grey | AK99: Like New | AL99: 11400 | AM99: 2026-12-27 | AN99: Kerala | AO99: Kochi | AP99: Available | AQ99: 2026-09-06 | AR99: Dealer | AS99: Yes | AT99: Yes | AU99: No | AV99: One-Touch Easy Electric Tumble 2nd Row, SkyLight Sunroof, Ventilated Front Seats, 64-Colour Ambient Light | AW99: Well-maintained 2025 like new condition Kia Carens Luxury Plus 1.5L Turbo DCT 7S (DCT) in Kochi. Powered by a 1482 cc petrol engine delivering 16.8 km/l. Complete service history available. | AX99: Family | AY99: 9900 | AZ99: Synthetic Sample
A100: CAR-1099 | B100: Kia | C100: Kia EV6 | D100: EV6 | E100: GT Line AWD 77.4 kWh | F100: 2025 | G100: 2025 | H100: Used | I100: SUV | J100: Electric | K100: Automatic | L100: 1 | M100: 5820000 | N100: 6430000 | O100: Yes | P100: 5585000 | Q100: 1455000 | R100: =IF(V100="No",0,MAX(0,M100-Q100)) -> 4365000 | S100: 10.4 | T100: 60 | U100: =IF(OR(R100<=0,S100<0,T100<=0),"",IF(S100=0,R100/T100,-PMT(S100/1200,T100,R100))) -> 93605 | V100: Yes | X100: 321 | Z100: 708 | AA100: 77.4 | AB100: 5 | AC100: 5 | AD100: 490 | AE100: 5 Star (Euro NCAP) | AF100: 8 | AG100: Yes | AH100: Yes | AI100: Yes | AJ100: Abyss Black | AK100: Like New | AL100: 10700 | AM100: 2027-03-05 | AN100: Gujarat | AO100: Ahmedabad | AP100: Available | AQ100: 2026-10-09 | AR100: Dealer | AS100: No | AT100: Yes | AU100: No | AV100: Dual Motor All-Wheel Drive, 0-100 km/h in 5.2s, AR Head-Up Display, Meridian 14-Speaker Audio | AW100: Well-maintained 2025 like new condition Kia EV6 GT Line AWD 77.4 kWh (Automatic) in Ahmedabad. Powered by a 77.4 kWh battery delivering 708 km certified range. Inspected for mechanical reliability. | AX100: Enthusiast | AY100: 7500 | AZ100: Synthetic Sample
...

Sheet Brand Summary
A1: INDIAN CAR MARKETPLACE — BRAND-LEVEL SUMMARY REPORT
A2: Note: All summary statistics dynamically calculate from the 'Car Listings' worksheet (rows 2 to 161). All monetary values in INR (₹).
A4: Brand | B4: Number of Listings | C4: Average Selling Price (INR) | D4: Minimum Price (INR) | E4: Maximum Price (INR)
A5: Audi | B5: =COUNTIF('Car Listings'!$B$2:$B$161, A5) -> 6 | C5: =AVERAGEIF('Car Listings'!$B$2:$B$161, A5, 'Car Listings'!$M$2:$M$161) -> 4661667 | D5: =SUMPRODUCT(MIN(('Car Listings'!$B$2:$B$161=A5)*('Car Listings'!$M$2:$M$161)+('Car Listings'!$B$2:$B$161<>A5)*1000000000)) -> 1040000 | E5: =SUMPRODUCT(MAX(('Car Listings'!$B$2:$B$161=A5)*('Car Listings'!$M$2:$M$161))) -> 12700000
A6: BMW | B6: =COUNTIF('Car Listings'!$B$2:$B$161, A6) -> 6 | C6: =AVERAGEIF('Car Listings'!$B$2:$B$161, A6, 'Car Listings'!$M$2:$M$161) -> 3058333 | D6: =SUMPRODUCT(MIN(('Car Listings'!$B$2:$B$161=A6)*('Car Listings'!$M$2:$M$161)+('Car Listings'!$B$2:$B$161<>A6)*1000000000)) -> 1065000 | E6: =SUMPRODUCT(MAX(('Car Listings'!$B$2:$B$161=A6)*('Car Listings'!$M$2:$M$161))) -> 5645000
A7: BYD | B7: =COUNTIF('Car Listings'!$B$2:$B$161, A7) -> 4 | C7: =AVERAGEIF('Car Listings'!$B$2:$B$161, A7, 'Car Listings'!$M$2:$M$161) -> 3555000 | D7: =SUMPRODUCT(MIN(('Car Listings'!$B$2:$B$161=A7)*('Car Listings'!$M$2:$M$161)+('Car Listings'!$B$2:$B$161<>A7)*1000000000)) -> 2645000 | E7: =SUMPRODUCT(MAX(('Car Listings'!$B$2:$B$161=A7)*('Car Listings'!$M$2:$M$161))) -> 4555000
A8: Honda | B8: =COUNTIF('Car Listings'!$B$2:$B$161, A8) -> 12 | C8: =AVERAGEIF('Car Listings'!$B$2:$B$161, A8, 'Car Listings'!$M$2:$M$161) -> 821250 | D8: =SUMPRODUCT(MIN(('Car Listings'!$B$2:$B$161=A8)*('Car Listings'!$M$2:$M$161)+('Car Listings'!$B$2:$B$161<>A8)*1000000000)) -> 315000 | E8: =SUMPRODUCT(MAX(('Car Listings'!$B$2:$B$161=A8)*('Car Listings'!$M$2:$M$161))) -> 1450000
A9: Hyundai | B9: =COUNTIF('Car Listings'!$B$2:$B$161, A9) -> 21 | C9: =AVERAGEIF('Car Listings'!$B$2:$B$161, A9, 'Car Listings'!$M$2:$M$161) -> 1233571 | D9: =SUMPRODUCT(MIN(('Car Listings'!$B$2:$B$161=A9)*('Car Listings'!$M$2:$M$161)+('Car Listings'!$B$2:$B$161<>A9)*1000000000)) -> 180000 | E9: =SUMPRODUCT(MAX(('Car Listings'!$B$2:$B$161=A9)*('Car Listings'!$M$2:$M$161))) -> 4065000
A10: Jeep | B10: =COUNTIF('Car Listings'!$B$2:$B$161, A10) -> 2 | C10: =AVERAGEIF('Car Listings'!$B$2:$B$161, A10, 'Car Listings'!$M$2:$M$161) -> 1962500 | D10: =SUMPRODUCT(MIN(('Car Listings'!$B$2:$B$161=A10)*('Car Listings'!$M$2:$M$161)+('Car Listings'!$B$2:$B$161<>A10)*1000000000)) -> 1065000 | E10: =SUMPRODUCT(MAX(('Car Listings'!$B$2:$B$161=A10)*('Car Listings'!$M$2:$M$161))) -> 2860000
A11: Kia | B11: =COUNTIF('Car Listings'!$B$2:$B$161, A11) -> 12 | C11: =AVERAGEIF('Car Listings'!$B$2:$B$161, A11, 'Car Listings'!$M$2:$M$161) -> 2194167 | D11: =SUMPRODUCT(MIN(('Car Listings'!$B$2:$B$161=A11)*('Car Listings'!$M$2:$M$161)+('Car Listings'!$B$2:$B$161<>A11)*1000000000)) -> 510000 | E11: =SUMPRODUCT(MAX(('Car Listings'!$B$2:$B$161=A11)*('Car Listings'!$M$2:$M$161))) -> 6595000
A12: MG | B12: =COUNTIF('Car Listings'!$B$2:$B$161, A12) -> 6 | C12: =AVERAGEIF('Car Listings'!$B$2:$B$161, A12, 'Car Listings'!$M$2:$M$161) -> 1255000 | D12: =SUMPRODUCT(MIN(('Car Listings'!$B$2:$B$161=A12)*('Car Listings'!$M$2:$M$161)+('Car Listings'!$B$2:$B$161<>A12)*1000000000)) -> 545000 | E12: =SUMPRODUCT(MAX(('Car Listings'!$B$2:$B$161=A12)*('Car Listings'!$M$2:$M$161))) -> 1550000
A13: Mahindra | B13: =COUNTIF('Car Listings'!$B$2:$B$161, A13) -> 15 | C13: =AVERAGEIF('Car Listings'!$B$2:$B$161, A13, 'Car Listings'!$M$2:$M$161) -> 1545600 | D13: =SUMPRODUCT(MIN(('Car Listings'!$B$2:$B$161=A13)*('Car Listings'!$M$2:$M$161)+('Car Listings'!$B$2:$B$161<>A13)*1000000000)) -> 615000 | E13: =SUMPRODUCT(MAX(('Car Listings'!$B$2:$B$161=A13)*('Car Listings'!$M$2:$M$161))) -> 2690000
A14: Maruti Suzuki | B14: =COUNTIF('Car Listings'!$B$2:$B$161, A14) -> 21 | C14: =AVERAGEIF('Car Listings'!$B$2:$B$161, A14, 'Car Listings'!$M$2:$M$161) -> 721571 | D14: =SUMPRODUCT(MIN(('Car Listings'!$B$2:$B$161=A14)*('Car Listings'!$M$2:$M$161)+('Car Listings'!$B$2:$B$161<>A14)*1000000000)) -> 150000 | E14: =SUMPRODUCT(MAX(('Car Listings'!$B$2:$B$161=A14)*('Car Listings'!$M$2:$M$161))) -> 1999000
A15: Mercedes-Benz | B15: =COUNTIF('Car Listings'!$B$2:$B$161, A15) -> 6 | C15: =AVERAGEIF('Car Listings'!$B$2:$B$161, A15, 'Car Listings'!$M$2:$M$161) -> 4096667 | D15: =SUMPRODUCT(MIN(('Car Listings'!$B$2:$B$161=A15)*('Car Listings'!$M$2:$M$161)+('Car Listings'!$B$2:$B$161<>A15)*1000000000)) -> 1685000 | E15: =SUMPRODUCT(MAX(('Car Listings'!$B$2:$B$161=A15)*('Car Listings'!$M$2:$M$161))) -> 7590000
A16: Renault | B16: =COUNTIF('Car Listings'!$B$2:$B$161, A16) -> 6 | C16: =AVERAGEIF('Car Listings'!$B$2:$B$161, A16, 'Car Listings'!$M$2:$M$161) -> 346667 | D16: =SUMPRODUCT(MIN(('Car Listings'!$B$2:$B$161=A16)*('Car Listings'!$M$2:$M$161)+('Car Listings'!$B$2:$B$161<>A16)*1000000000)) -> 185000 | E16: =SUMPRODUCT(MAX(('Car Listings'!$B$2:$B$161=A16)*('Car Listings'!$M$2:$M$161))) -> 540000
... A20: Volkswagen | B20: =COUNTIF('Car Listings'!$B$2:$B$161, A20) -> 4 | C20: =AVERAGEIF('Car Listings'!$B$2:$B$161, A20, 'Car Listings'!$M$2:$M$161) -> 1117500 | D20: =SUMPRODUCT(MIN(('Car Listings'!$B$2:$B$161=A20)*('Car Listings'!$M$2:$M$161)+('Car Listings'!$B$2:$B$161<>A20)*1000000000)) -> 615000 | E20: =SUMPRODUCT(MAX(('Car Listings'!$B$2:$B$161=A20)*('Car Listings'!$M$2:$M$161))) -> 1535000
A21: Total / Overall Market | B21: =SUM(B5:B20) -> 160 | C21: =AVERAGE('Car Listings'!$M$2:$M$161) -> 1643119 | D21: =MIN('Car Listings'!$M$2:$M$161) -> 150000 | E21: =MAX('Car Listings'!$M$2:$M$161) -> 12700000

Sheet Data Dictionary
A1: DATA DICTIONARY & SYNTHETIC DATA DOCUMENTATION
A2: Limitations of Synthetic Data: Vehicle technical specs and safety ratings reflect verified manufacturer/NCAP reference data. Listing IDs, prices, odometer readings, and availability are synthetic samples for AI assistant testing. Interest rates and EMIs are illustrative estimates, not binding lender offers.
A3: Excel Col | B3: Column Name | C3: Section / Category | D3: Data Type | E3: Units / Format | F3: Data Nature | G3: Description & Formula / Validation Rule | H3: Example Value
A4: A | B4: Listing ID | C4: Basic Information | D4: String | E4: Alphanumeric ID | F4: Synthetic Sample | G4: Unique primary key identifier for each vehicle listing (CAR-1001 to CAR-1160). | H4: CAR-1001
A5: B | B5: Brand | C5: Basic Information | D5: String | E5: Text | F5: Verified Spec | G5: Automobile manufacturer / OEM brand name in the Indian market. | H5: Maruti Suzuki
A6: C | B6: Car Name | C6: Basic Information | D6: String | E6: Text | F6: Verified Spec | G6: Full commercial vehicle name combining Brand and Model. | H6: Maruti Suzuki Swift
A7: D | B7: Model | C7: Basic Information | D7: String | E7: Text | F7: Verified Spec | G7: Specific vehicle model line. | H7: Swift
A8: E | B8: Variant | C8: Basic Information | D8: String | E8: Text | F8: Verified Spec | G8: Manufacturer trim level and powertrain badge. | H8: ZXi+ 1.2L DualJet
A9: F | B9: Manufacturing Year | C9: Basic Information | D9: Integer | E9: Year (YYYY) | F9: Synthetic Sample | G9: Year the vehicle was manufactured (2015–2026). | H9: 2024
A10: G | B10: Registration Year | C10: Basic Information | D10: Integer | E10: Year (YYYY) | F10: Synthetic Sample | G10: Year the vehicle was registered with the RTO (>= Manufacturing Year). | H10: 2024
A11: H | B11: New or Used | C11: Basic Information | D11: Categorical | E11: Dropdown | F11: Synthetic Sample | G11: Indicates whether the vehicle is a brand-new showroom unit or pre-owned. | H11: Used
A12: I | B12: Vehicle Type | C12: Basic Information | D12: Categorical | E12: Dropdown | F12: Verified Spec | G12: Body style classification (Hatchback, Sedan, SUV, MUV, Luxury, Coupe). | H12: SUV
A13: J | B13: Fuel Type | C13: Basic Information | D13: Categorical | E13: Dropdown | F13: Verified Spec | G13: Primary propulsion fuel/energy type (Petrol, Diesel, Electric, CNG, Hybrid). | H13: Petrol
A14: K | B14: Transmission | C14: Basic Information | D14: Categorical | E14: Dropdown | F14: Verified Spec | G14: Gearbox type (Manual, Automatic, AMT, CVT, DCT). | H14: DCT
... A55: AZ | B55: Source Type | C55: Additional Information | D55: Categorical | E55: Verified Source / Synthetic Sample | F55: Metadata | G55: Explicitly labels whether the listing row is a live verified listing or a synthetic sample. | H55: Synthetic Sample
A56: BA | B56: Source URL | C56: Additional Information | D56: String (Nullable) | E56: URL | F56: Metadata | G56: Left intentionally blank for Synthetic Sample rows to avoid inventing live URLs.

Sheet EMI Calculator
A1: INTERACTIVE AUTOMOBILE LOAN & EMI CALCULATOR (REDUCING-BALANCE FORMULA)
A2: Disclaimer: Interest rates and monthly EMI values are illustrative estimates for AI assistant simulation and financial planning, not binding lender offers.
A4: Parameter / Metric | B4: Input / Calculated Value | C4: Unit & Formula Explanation | D4: Notes
A5: Vehicle Selling Price (INR) | B5: 1250000 | C5: INR (User Editable Input) | D5: Change this value to test
A6: Down Payment (INR) | B6: 250000 | C6: INR (User Editable Input) | D6: Upfront margin paid by buyer
A7: Principal Loan Amount (INR) | B7: =MAX(0,B5-B6) -> 1000000 | C7: Formula: =MAX(0, B5-B6) | D7: Automatically updates
A8: Annual Interest Rate (% per annum) | B8: 9.25 | C8: % per annum (User Editable Input) | D8: Set to 0 to verify zero-interest loan
A9: EMI Tenure (Months) | B9: 60 | C9: Months (User Editable Input) | D9: Standard tenures: 12 to 84 months
A10: Estimated Monthly EMI (INR) | B10: =IF(OR(B7<=0,B8<0,B9<=0),"",IF(B8=0,B7/B9,-PMT(B8/1200,B9,B7))) -> 20880 | C10: Formula: =IF(OR(B7<=0,B8<0,B9<=0),"",IF(B8=0,B7/B9,-PMT(B8/1200,B9,B7))) | D10: Illustrative Monthly Installment
A11: Total Amount Payable on Loan (INR) | B11: =IF(B10="","",B10*B9) -> 1252792 | C11: Formula: =IF(B10="","",B10*B9) | D11: Principal + Total Interest
A12: Total Interest Payable (INR) | B12: =IF(B11="","",MAX(0,B11-B7)) -> 252792 | C12: Formula: =IF(B11="","",MAX(0,B11-B7)) | D12: Total cost of borrowing
A13: Total On-Road Outflow incl. Down Payment (INR) | B13: =IF(B11="","",B6+B11) -> 1502792 | C13: Formula: =IF(B11="","",B6+B11) | D13: Down Payment + Total EMIs
A15: Tenure Sensitivity Comparison (Months) | B15: Estimated Monthly EMI (INR) | C15: Total Interest Payable (INR) | D15: Total Loan Repayment (INR)
A16: 12 | B16: =IF(OR($B$7<=0,$B$8<0,A16<=0),"",IF($B$8=0,$B$7/A16,-PMT($B$8/1200,A16,$B$7))) -> 87567 | C16: =IF(B16="","",(B16*A16)-$B$7) -> 50804 | D16: =IF(B16="","",B16*A16) -> 1050804
A17: 24 | B17: =IF(OR($B$7<=0,$B$8<0,A17<=0),"",IF($B$8=0,$B$7/A17,-PMT($B$8/1200,A17,$B$7))) -> 45800 | C17: =IF(B17="","",(B17*A17)-$B$7) -> 99200 | D17: =IF(B17="","",B17*A17) -> 1099200
A18: 36 | B18: =IF(OR($B$7<=0,$B$8<0,A18<=0),"",IF($B$8=0,$B$7/A18,-PMT($B$8/1200,A18,$B$7))) -> 31916 | C18: =IF(B18="","",(B18*A18)-$B$7) -> 148976 | D18: =IF(B18="","",B18*A18) -> 1148976
A19: 48 | B19: =IF(OR($B$7<=0,$B$8<0,A19<=0),"",IF($B$8=0,$B$7/A19,-PMT($B$8/1200,A19,$B$7))) -> 25004 | C19: =IF(B19="","",(B19*A19)-$B$7) -> 200192 | D19: =IF(B19="","",B19*A19) -> 1200192
A20: 60 | B20: =IF(OR($B$7<=0,$B$8<0,A20<=0),"",IF($B$8=0,$B$7/A20,-PMT($B$8/1200,A20,$B$7))) -> 20880 | C20: =IF(B20="","",(B20*A20)-$B$7) -> 252800 | D20: =IF(B20="","",B20*A20) -> 1252800
A21: 72 | B21: =IF(OR($B$7<=0,$B$8<0,A21<=0),"",IF($B$8=0,$B$7/A21,-PMT($B$8/1200,A21,$B$7))) -> 18150 | C21: =IF(B21="","",(B21*A21)-$B$7) -> 306800 | D21: =IF(B21="","",B21*A21) -> 1306800
A22: 84 | B22: =IF(OR($B$7<=0,$B$8<0,A22<=0),"",IF($B$8=0,$B$7/A22,-PMT($B$8/1200,A22,$B$7))) -> 16216 | C22: =IF(B22="","",(B22*A22)-$B$7) -> 362144 | D22: =IF(B22="","",B22*A22) -> 1362144
